{
  "analysis_mode": "HISTORICAL_ONLY",
  "report_version": "5.0",
  "symbol": "ESYS.L",
  "generated_at": "2026-01-29T13:23:51.786715+00:00",
  "comprehensive_apex": {
    "score": 12,
    "rating": "LOW QUALITY",
    "color": "#ef4444",
    "calculation": "(40\u00d725% + 15\u00d720% + 52.5\u00d730% + 44\u00d725%) \u00d7 0.3 = 12",
    "components": {
      "setup": {
        "score": 40,
        "weight": 0.25
      },
      "trust": {
        "score": 15,
        "weight": 0.2
      },
      "panic": {
        "score": 52.5,
        "weight": 0.3
      },
      "compression": {
        "score": 44,
        "weight": 0.25
      }
    },
    "timing": {
      "regime": "BROKEN",
      "multiplier": 0.3
    }
  },
  "top_card": {
    "ticker": "ESYS.L",
    "company_name": "essensys plc",
    "sector": "Technology",
    "market_cap_gbp": 10207785,
    "days_active": 1185,
    "apex_score_100": 40,
    "confidence_score_100": 15,
    "panic_score_100": 52.5,
    "cc_score_100": 44,
    "ai_final_score_25": 15,
    "ai_strength": "STRONG",
    "timing_regime": "BROKEN",
    "action": "AVOID",
    "thesis_one_liner": "AVOID - BROKEN timing with 40/100 opportunity score",
    "overall_score_100": 38
  },
  "enrichment": {
    "company_info": {
      "name": "essensys plc",
      "sector": "Technology",
      "industry": "Software - Application",
      "exchange": "LSE",
      "market": "AIM",
      "currency": "GBP",
      "risk_tier": "High Risk",
      "current_market_cap": 10207785,
      "current_close_price": 15.75
    },
    "basics": {
      "ticker": "ESYS.L",
      "current_price": 15.75,
      "ath": 310.0,
      "atl": 13.0,
      "ath_date": "2021-08-02",
      "atl_date": "2024-04-30",
      "week_52_high": 39.0,
      "week_52_low": 13.0,
      "week_52_high_date": "2025-01-28",
      "week_52_low_date": "2026-01-06",
      "drawdown_from_ath_pct": 94.92,
      "data_start": "2020-01-02",
      "data_end": "2026-01-28",
      "total_bars": 1534
    },
    "latest_signal": {
      "date": "2022-10-31",
      "scan_date": "2026-01-26",
      "signal_type": "DEEP CRASH BOTTOM",
      "signal_color": "GREEN",
      "price": 45.0,
      "drawdown_pct": 85.0,
      "ai_score": 12.0,
      "rsi": 8.5,
      "cycle_position": 0.0476,
      "holding_period_days": 1185,
      "current_pnl_pct": -65.0,
      "rally_state": "accumulating",
      "distance_from_high_pct": -73.77,
      "Rally_Count": 1,
      "days_since_last_high": 34,
      "last_high_date": "2025-12-23",
      "lock_in_reached": true,
      "lock_in_date": "2023-04-05",
      "best_rally_pct": 35.56
    },
    "best_historical_signal": {
      "signal_date": "2022-10-31",
      "signal_type": "DEEP CRASH BOTTOM",
      "signal_color": "GREEN",
      "entry_price": 45.0,
      "peak_price": 62.0,
      "peak_date": "2023-04-17",
      "rally_pct": 37.78,
      "days_to_peak": 168,
      "ai_score": 12.0
    },
    "all_historical_signals": [
      {
        "signal_id": "ESYS.L_2022-08-19",
        "signal_date": "2022-08-19",
        "signal_type": "CRASH ZONE BOTTOM",
        "signal_color": "YELLOW",
        "entry_price": 60.5,
        "current_price": 16.0,
        "current_return_pct": -73.55,
        "best_rally_pct": 0.83,
        "best_rally_date": "2023-04-05",
        "rally_state": "accumulating",
        "Rally_Count": 0,
        "distance_from_high_pct": -73.77,
        "days_since_last_high": 34,
        "lock_in_reached": true,
        "age_days": 1256,
        "status": "historical"
      },
      {
        "signal_id": "ESYS.L_2022-08-24",
        "signal_date": "2022-08-24",
        "signal_type": "CRASH ZONE BOTTOM",
        "signal_color": "YELLOW",
        "entry_price": 59.0,
        "current_price": 16.0,
        "current_return_pct": -72.88,
        "best_rally_pct": 3.39,
        "best_rally_date": "2023-04-05",
        "rally_state": "accumulating",
        "Rally_Count": 0,
        "distance_from_high_pct": -73.77,
        "days_since_last_high": 34,
        "lock_in_reached": true,
        "age_days": 1251,
        "status": "historical"
      },
      {
        "signal_id": "ESYS.L_2022-08-25",
        "signal_date": "2022-08-25",
        "signal_type": "CRASH ZONE BOTTOM",
        "signal_color": "YELLOW",
        "entry_price": 58.0,
        "current_price": 16.0,
        "current_return_pct": -72.41,
        "best_rally_pct": 5.17,
        "best_rally_date": "2023-04-05",
        "rally_state": "accumulating",
        "Rally_Count": 0,
        "distance_from_high_pct": -73.77,
        "days_since_last_high": 34,
        "lock_in_reached": true,
        "age_days": 1250,
        "status": "historical"
      },
      {
        "signal_id": "ESYS.L_2022-08-26",
        "signal_date": "2022-08-26",
        "signal_type": "CRASH ZONE BOTTOM",
        "signal_color": "YELLOW",
        "entry_price": 58.5,
        "current_price": 16.0,
        "current_return_pct": -72.65,
        "best_rally_pct": 4.27,
        "best_rally_date": "2023-04-05",
        "rally_state": "accumulating",
        "Rally_Count": 0,
        "distance_from_high_pct": -73.77,
        "days_since_last_high": 34,
        "lock_in_reached": true,
        "age_days": 1249,
        "status": "historical"
      },
      {
        "signal_id": "ESYS.L_2022-08-30",
        "signal_date": "2022-08-30",
        "signal_type": "CRASH ZONE BOTTOM",
        "signal_color": "YELLOW",
        "entry_price": 58.5,
        "current_price": 16.0,
        "current_return_pct": -72.65,
        "best_rally_pct": 4.27,
        "best_rally_date": "2023-04-05",
        "rally_state": "accumulating",
        "Rally_Count": 0,
        "distance_from_high_pct": -73.77,
        "days_since_last_high": 34,
        "lock_in_reached": true,
        "age_days": 1245,
        "status": "historical"
      },
      {
        "signal_id": "ESYS.L_2022-08-31",
        "signal_date": "2022-08-31",
        "signal_type": "CRASH ZONE BOTTOM",
        "signal_color": "YELLOW",
        "entry_price": 59.0,
        "current_price": 16.0,
        "current_return_pct": -72.88,
        "best_rally_pct": 3.39,
        "best_rally_date": "2023-04-05",
        "rally_state": "accumulating",
        "Rally_Count": 0,
        "distance_from_high_pct": -73.77,
        "days_since_last_high": 34,
        "lock_in_reached": true,
        "age_days": 1244,
        "status": "historical"
      },
      {
        "signal_id": "ESYS.L_2022-09-01",
        "signal_date": "2022-09-01",
        "signal_type": "CRASH ZONE BOTTOM",
        "signal_color": "YELLOW",
        "entry_price": 59.0,
        "current_price": 16.0,
        "current_return_pct": -72.88,
        "best_rally_pct": 3.39,
        "best_rally_date": "2023-04-05",
        "rally_state": "accumulating",
        "Rally_Count": 0,
        "distance_from_high_pct": -73.77,
        "days_since_last_high": 34,
        "lock_in_reached": true,
        "age_days": 1243,
        "status": "historical"
      },
      {
        "signal_id": "ESYS.L_2022-10-06",
        "signal_date": "2022-10-06",
        "signal_type": "CRASH ZONE BOTTOM",
        "signal_color": "YELLOW",
        "entry_price": 53.0,
        "current_price": 16.0,
        "current_return_pct": -69.81,
        "best_rally_pct": 15.09,
        "best_rally_date": "2023-04-05",
        "rally_state": "accumulating",
        "Rally_Count": 1,
        "distance_from_high_pct": -73.77,
        "days_since_last_high": 34,
        "lock_in_reached": true,
        "age_days": 1208,
        "status": "historical"
      },
      {
        "signal_id": "ESYS.L_2022-10-19",
        "signal_date": "2022-10-19",
        "signal_type": "CRASH ZONE BOTTOM",
        "signal_color": "YELLOW",
        "entry_price": 45.5,
        "current_price": 16.0,
        "current_return_pct": -64.84,
        "best_rally_pct": 34.07,
        "best_rally_date": "2023-04-05",
        "rally_state": "accumulating",
        "Rally_Count": 1,
        "distance_from_high_pct": -73.77,
        "days_since_last_high": 34,
        "lock_in_reached": true,
        "age_days": 1195,
        "status": "historical"
      },
      {
        "signal_id": "ESYS.L_2022-10-20",
        "signal_date": "2022-10-20",
        "signal_type": "CRASH ZONE BOTTOM",
        "signal_color": "YELLOW",
        "entry_price": 45.6,
        "current_price": 16.0,
        "current_return_pct": -64.91,
        "best_rally_pct": 33.77,
        "best_rally_date": "2023-04-05",
        "rally_state": "accumulating",
        "Rally_Count": 1,
        "distance_from_high_pct": -73.77,
        "days_since_last_high": 34,
        "lock_in_reached": true,
        "age_days": 1194,
        "status": "historical"
      },
      {
        "signal_id": "ESYS.L_2022-10-24",
        "signal_date": "2022-10-24",
        "signal_type": "CRASH ZONE BOTTOM",
        "signal_color": "YELLOW",
        "entry_price": 45.5,
        "current_price": 16.0,
        "current_return_pct": -64.84,
        "best_rally_pct": 34.07,
        "best_rally_date": "2023-04-05",
        "rally_state": "accumulating",
        "Rally_Count": 1,
        "distance_from_high_pct": -73.77,
        "days_since_last_high": 34,
        "lock_in_reached": true,
        "age_days": 1190,
        "status": "historical"
      },
      {
        "signal_id": "ESYS.L_2022-10-31",
        "signal_date": "2022-10-31",
        "signal_type": "DEEP CRASH BOTTOM",
        "signal_color": "GREEN",
        "entry_price": 45.0,
        "current_price": 16.0,
        "current_return_pct": -64.44,
        "best_rally_pct": 35.56,
        "best_rally_date": "2023-04-05",
        "rally_state": "accumulating",
        "Rally_Count": 1,
        "distance_from_high_pct": -73.77,
        "days_since_last_high": 34,
        "lock_in_reached": true,
        "age_days": 1183,
        "status": "historical"
      }
    ],
    "stats": {
      "total_signals": 12,
      "win_rate_pct": 100.0,
      "avg_rally_pct": 17.07,
      "median_rally_pct": 7.17,
      "best_rally_pct": 37.78,
      "worst_rally_pct": 5.08
    },
    "splits": [],
    "split_risk": {
      "split_detected": false,
      "risk_level": "NONE",
      "confidence": "HIGH"
    },
    "data_quality": {
      "price_reliability": "RELIABLE",
      "pnl_reliability": "RELIABLE",
      "overall_confidence": "HIGH"
    },
    "risk_flags": [
      "EXTREME_DRAWDOWN",
      "FREQUENT_CRASHES"
    ],
    "last_updated": "2026-01-29 10:04:49 UTC",
    "volatility": {
      "atr_normalized": 9.15,
      "stddev_20d": 0.0
    },
    "trends": {
      "intelligence_signal": "ACCUMULATION"
    }
  },
  "decision_summary": {
    "why_it_matters": [
      "APEX 40/100 indicates moderate opportunity quality",
      "Timing regime: BROKEN",
      "Historical profile: 1 rallies, 36% best run"
    ],
    "main_risk": "Confidence 15/100 - full data loaded",
    "watch_next": [
      "RNS catalysts (funding/operational updates)",
      "Volume expansion confirmation",
      "Timing regime change signals"
    ]
  },
  "triangulation": {
    "rns": {
      "has_data": true,
      "ticker": "ESYS.L",
      "latest": [
        {
          "title": "Directorate change",
          "date": "28th Jan 2026",
          "announcement_date": "28th Jan 2026",
          "release_time": "7:00 am",
          "source": "RNS",
          "content": "28 Jan 2026 07:00\nRNS Number : 6266Q\nessensys PLC\n28 January 2026\n28 January 2026\nessensys plc\n(\"essensys\" or \"Group\")\nDirectorate Change\n\u200b\nessensys plc (AIM:ESYS), the leading global provider of software and technology to the flexible workspace industry, announces that Greg Price, Chief Financial Officer, has informed the Board of his decision to resign from the Company to take up the role of Chief Financial Officer with Cerillion plc, the billing, charging and customer relationship management software solutions provider.\n\u200b\nGreg will stay with essensys until the end of April 2026 and will assist the Board during this period to enable an orderly handover until such time as a successor has been appointed.\n\u200b\nessensys' Chairman Jon Lee said:\n\"On behalf of the Board, I would like to thank Greg for his significant contribution to the Group during his tenure as Chief Financial Officer. He has played a key role in strengthening the Group's financial position, enhancing financial discipline across the business, and supporting the delivery of the Group's strategy during a period of change. The Board is grateful for his commitment and leadership, and we wish him every success in his future endeavours.\"\n-Ends-\nFor further information, please contact:\n\u200b\nessensys plc\n+44 (0)20 3102 5252\nJon Lee, Chairman\nJames Lowery, Chief Executive Officer\nGreg Price, Chief Financial Officer\nCanaccord Genuity Limited (Nominated Adviser and Broker)\n+44 (0)20 7523 8000\nSimon Bridges / Harry Gooden / Andrew Potts /Elizabeth Halley-Stott\nGracechurch Group\nHeather Armstrong / Alexis Gore / Rebecca Scott\n+44 (0) 20 4582 3500\nessensys@gracechurchpr.com\nAbout essensys plc\nFounded in 2006 and listed on the London Stock Exchange AIM Market, essensys is a leading global provider of software and technology to the commercial real estate industry.\n\u200b\nPartnering with many of the world's leading landlords and flexible workspace operators, essensys delivers innovative digital experience (DX) solutions that drive occupancy, maximise yield and reduce operating costs. Its flagship products, essensys Platform and elumo, solve the complex challenges of managing physical and digital access in dynamic multi-tenant environments, while delivering deep space utilisation insights and transformative digital experiences.\n\u200b\nWith a focus on Access, Intelligence & Experience, essensys' products enable real estate leaders to unlock the full potential of their portfolios in today's flexible, hybrid world while ensuring they stay ahead in an era of dynamic workplace evolution.\nThis information is provided by RNS, the news service of the London Stock Exchange. RNS is approved by the Financial Conduct Authority to act as a Primary Information Provider in the United Kingdom. Terms and conditions relating to the use and distribution of this information may apply. For further information, please contact\nrns@lseg.com\nor visit\nwww.rns.com\n.RNS may use your IP address to confirm compliance with the terms and conditions, to analyse how you engage with the information contained in this communication, and to share such analysis on an anonymised basis with others as part of our commercial services. For further information about how RNS and the London Stock Exchange use the personal data you provide us, please see our\nPrivacy Policy\n.\nEND\nBOABRMLTMTITBMF",
          "rns_number": "RNS Number : 6266Q"
        },
        {
          "title": "Exercise of Options, TVR & Rule 2.9 Announcement",
          "date": "26th Jan 2026",
          "announcement_date": "26th Jan 2026",
          "release_time": "7:00 am",
          "source": "RNS",
          "content": "26 Jan 2026 07:00\nRNS Number : 2401Q\nessensys PLC\n26 January 2026\n26 January 2026\nessensys plc\n(\"essensys\" or the \"Company\")\n\u200b\nExercise of Options and Total Voting Rights & Rule 2.9 Announcement\n\u200b\nessensys plc (AIM:ESYS), the leading global provider of software and technology to the flexible workspace industry, announces that it has issued and allotted 15,348 new ordinary shares of 0.25 pence each (\"Ordinary Shares\") following the exercise of share options by an employee of the Company.\n\u200b\nApplication has been made to the London Stock Exchange for the 15,348 new Ordinary Shares to be admitted to trading on AIM (\"Admission\") and it is expected that Admission will become effective and trading will commence at 8.00 a.m. on 28 January 2026.\n\u200b\nThe Company advises that, following Admission, the Company's issued share capital will be 64,811,336 Ordinary Shares. The Company does not hold any Ordinary Shares in treasury. As such the Company's total number of Ordinary Shares with voting rights is 64,811,336.\n\u200b\nThe above figure of 64,811,336 may be used by shareholders as the denominator for the calculations by which they will determine if they are required to notify their interest in, or a change to their interest in, the Company under the FCA's Disclosure Guidance and Transparency Rules.\n\u200b\nIn accordance with Rule 2.9 of the City Code on Takeovers and Mergers (the \"Code\"), essensys confirms that, as at the date and time of this announcement, its issued share capital consisted of 64,811,336 Ordinary Shares\nof 0.25 pence each which are admitted to trading on the AIM market of London Stock Exchange plc. The International Securities Identification Number for the Company's Ordinary Shares is GB00BJL1ZF49 and the Legal Entity Identifier is 2138002MSI4WKYNOBS73.\n-Ends-\nFor further information, please contact:\nessensys plc\n+44 (0)20 3102 5252\nJames Lowery, Chief Executive Officer\nGreg Price, Chief Financial Officer\nCanaccord Genuity Limited (Nominated Adviser and Broker)\n+44 (0)20 7523 8000\nSimon Bridges / Harry Gooden / Andrew Potts / Elizabeth Halley-Stott\nGracechurch Group\nHeather Armstrong / Alexis Gore / Rebecca Scott\n+44 (0) 20 4582 3500\nessensys@gracechurchpr.com\nAbout essensys plc\n\u200b\nessensys is the leading provider of software and technology to landlords and flexible workspace operators. Founded in 2006 and listed on the AIM market since 2019, essensys' mission is to power the world's largest community of flexible, technology-driven spaces. Under new leadership, the Company has simplified its go-to-market strategy around two core offerings: essensys Platform and elumo.\n\u200b\nessensys Platform is a SaaS platform that delivers enterprise-grade Wi-Fi seamlessly across portfolios of multi-tenant workspaces, while providing data insights to optimise performance. The Group's latest offering, elumo, provides customers with a new way to manage and monetise bookable spaces. The integrated bookings and access solution transforms meeting rooms and shared spaces from operational headaches into revenue-generating assets.\n\u200b\nWith customers in the UK, Europe, North America and APAC, essensys is deploying a newly launched and simplified go-to-market strategy, positioning the business long-term growth in the flexible workspace and commercial real estate market.\n\u200b\nImportant notices\n\u200b\nThis announcement is not intended to, and does not, constitute or form part of any offer, invitation or the solicitation of an offer to purchase, otherwise acquire, subscribe for, sell or otherwise dispose of, any securities, or the solicitation of any vote or approval in any jurisdiction, pursuant to this announcement or otherwise.\nThe distribution of this announcement in jurisdictions outside the United Kingdom may be restricted by law and therefore persons into whose possession this announcement comes should inform themselves about, and observe, such restrictions. Any failure to comply with the restrictions may constitute a violation of the securities law of any such jurisdiction.\n\u200b\nCanaccord Genuity Limited (\"\nCanaccord Genuity\n\"), which is authorised and regulated in the United Kingdom by the Financial Conduct Authority, is acting exclusively for essensys and for no-one else in connection with the matters referred to in this announcement and will not be responsible to any person other than essensys for providing the protections afforded to clients of Canaccord Genuity, nor for providing advice in relation to the matters referred to herein. Neither Canaccord Genuity nor any of its affiliates (nor any of its or their respective directors, officers, employees, representatives or agents) owes or accepts any duty, liability or responsibility whatsoever (whether direct or indirect, whether in contract, in tort, under statute or otherwise) to any person who is not a client of Canaccord Genuity in connection with the matters referred to in this announcement, or otherwise.\n\u200b\nDisclosure requirements of the Code\n\u200b\nUnder Rule 8.3(a) of the Code, any person who is interested in 1% or more of any class of relevant securities of an offeree company or of any securities exchange offeror (being any offeror other than an offeror in respect of which it has been announced that its offer is, or is likely to be, solely in cash) must make an Opening Position Disclosure following the commencement of the offer period and, if later, following the announcement in which any securities exchange offeror is first identified. An Opening Position Disclosure must contain details of the person's interests and short positions in, and rights to subscribe for, any relevant securities of each of (i) the offeree company and (ii) any securities exchange offeror(s). An Opening Position Disclosure by a person to whom Rule 8.3(a) applies must be made by no later than 3.30 pm (London time) on the 10th business day following the commencement of the offer period and, if appropriate, by no later than 3.30 pm (London time) on the 10th business day following the announcement in which any securities exchange offeror is first identified. Relevant persons who deal in the relevant securities of the offeree company or of a securities exchange offeror prior to the deadline for making an Opening Position Disclosure must instead make a Dealing Disclosure.\n\u200b\nUnder Rule 8.3(b) of the Code, any person who is, or becomes, interested in 1% or more of any class of relevant securities of the offeree company or of any securities exchange offeror must make a Dealing Disclosure if the person deals in any relevant securities of the offeree company or of any securities exchange offeror. A Dealing Disclosure must contain details of the dealing concerned and of the person's interests and short positions in, and rights to subscribe for, any relevant securities of each of (i) the offeree company and (ii) any securities exchange offeror, save to the extent that these details have previously been disclosed under Rule 8. A Dealing Disclosure by a person to whom Rule 8.3(b) applies must be made by no later than 3.30 pm (London time) on the business day following the date of the relevant dealing.\n\u200b\nIf two or more persons act together pursuant to an agreement or understanding, whether formal or informal, to acquire or control an interest in relevant securities of an offeree company or a securities exchange offeror, they will be deemed to be a single person for the purpose of Rule 8.3.\n\u200b\nOpening Position Disclosures must also be made by the offeree company and by any offeror and Dealing Disclosures must also be made by the offeree company, by any offeror and by any persons acting in concert with any of them (see Rules 8.1, 8.2 and 8.4). Details of the offeree and offeror companies in respect of whose relevant securities Opening Position Disclosures and Dealing Disclosures must be made can be found in the Disclosure Table on the Takeover Panel's website at\nwww.thetakeoverpanel.org.uk\n, including details of the number of relevant securities in issue, when the offer period commenced and when any offeror was first identified. You should contact the Panel's Market Surveillance Unit on +44 (0)20 7638 0129 if you are in any doubt as to whether you are required to make an Opening Position Disclosure or a Dealing Disclosure.\n\u200b\nThe defined terms used in this section \"Disclosure requirements of the Code\" are defined in the Code which can be found on the Takeover Panel's website.\nThis information is provided by RNS, the news service of the London Stock Exchange. RNS is approved by the Financial Conduct Authority to act as a Primary Information Provider in the United Kingdom. Terms and conditions relating to the use and distribution of this information may apply. For further information, please contact\nrns@lseg.com\nor visit\nwww.rns.com\n.RNS may use your IP address to confirm compliance with the terms and conditions, to analyse how you engage with the information contained in this communication, and to share such analysis on an anonymised basis with others as part of our commercial services. For further information about how RNS and the London Stock Exchange use the personal data you provide us, please see our\nPrivacy Policy\n.\nEND\nIOEBJMRTMTATBBF",
          "rns_number": "RNS Number : 2401Q"
        },
        {
          "title": "Extension of PUSU Deadline",
          "date": "23rd Jan 2026",
          "announcement_date": "23rd Jan 2026",
          "release_time": "12:30 pm",
          "source": "RNS",
          "content": "23 Jan 2026 12:30\nRNS Number : 2015Q\nessensys PLC\n23 January 2026\n23 January 2026\nNOT FOR RELEASE, PUBLICATION OR DISTRIBUTION IN WHOLE OR IN PART, DIRECTLY OR INDIRECTLY, IN, INTO OR FROM ANY JURISDICTION WHERE TO DO SO WOULD CONSTITUTE A VIOLATION OF THE RELEVANT LAWS OR REGULATIONS OF THAT JURISDICTION.\nTHIS IS AN ANNOUNCEMENT (THE \"ANNOUNCEMENT\") FALLING UNDER RULE 2.4 OF THE CITY CODE ON TAKEOVERS AND MERGERS (THE \"CODE\") AND DOES NOT CONSTITUTE AN ANNOUNCEMENT OF A FIRM INTENTION TO MAKE AN OFFER UNDER RULE 2.7 OF THE CODE AND THERE CAN BE NO CERTAINTY THAT AN OFFER WILL BE MADE.\nTHIS ANNOUNCEMENT CONTAINS INSIDE INFORMATION.\nFOR IMMEDIATE RELEASE.\nessensys plc\n(\"essensys\", the \"Company\" and together with its subsidiary undertakings, the \"Group\")\nExtension of PUSU Deadline\nOn 28 November 2025, the independent directors of essensys plc (AIM:ESYS), (being the full board except for Mark Furness) (the \"\nIndependent Directors\n\") confirmed that Mark Furness, founder and a Non-Executive Director, has submitted a preliminary, indicative, non-binding proposal to the Independent Directors relating to a possible all-cash offer for the entire issued and to be issued share capital of the Company at 20 pence per share (the \"\nAnnouncement\n\").\nThe Announcement stated that in accordance with Rule 2.6(a) of the Code, Mark Furness (or BidCo, once incorporated) must, by no later than 5.00 p.m. on 26 December 2025 (the \"\nPUSU Deadline\n\") either to announce a firm intention to make an offer for the Company in accordance with Rule 2.7 of the Code or to announce that it does not intend to make such an offer, in which case the announcement will be treated as a statement to which Rule 2.8 of the Code applies. As announced by the Company on 24 December 2025, that deadline was subsequently extended to 5.00 pm on 23 January 2026.\nDiscussions between the Company and Mark Furness remain ongoing. Therefore, the Board of essensys has requested, and the Panel has consented to, an extension of the PUSU Deadline in accordance with Rule 2.6(c) of the Code. In accordance with Rule 2.6(a) of the Code, Mark Furness is now required by no later than 5.00 p.m. on 20 February 2026 (the \"\nRevised PUSU Deadline\n\") to either announce a firm intention to make an offer for the Company in accordance with Rule 2.7 of the Code or announce that it does not intend to make such an offer, in which case the announcement will be treated as a statement to which Rule 2.8 of the Code applies. The Revised PUSU Deadline can be extended with the consent of the Panel in accordance with Rule 2.6(c) of the Code.\nThere can be no certainty that any firm offer will be made for the Company, nor as to the terms on which any such offer might be made.\nFurther announcements will be made as and when appropriate.\n-Ends-\nFor further information, please contact:\nessensys plc\n+44 (0)20 3102 5252\nJames Lowery, Chief Executive Officer\nGreg Price, Chief Financial Officer\nCanaccord Genuity Limited (Financial Adviser, Nominated Adviser and Broker)\n+44 (0)20 7523 8000\nSimon Bridges /\u00a0Harry Gooden / Andrew Potts / Elizabeth Halley-Stott\nGracechurch Group\nHeather Armstrong / Alexis Gore / Rebecca Scott\n+44 (0) 20 4582 3500\nessensys@gracechurchpr.com\nAbout essensys plc\nessensys is the leading provider of software and technology to landlords and flexible workspace operators. Founded in 2006 and listed on the AIM market since 2019, essensys' mission is to power the world's largest community of flexible, technology-driven spaces. Under new leadership, the Company has simplified its go-to-market strategy around two core offerings: essensys Platform and elumo.\nessensys Platform is a SaaS platform that delivers enterprise-grade Wi-Fi seamlessly across portfolios of multi-tenant workspaces, while providing data insights to optimise performance. The Group's latest offering, elumo, provides customers with a new way to manage and monetise bookable spaces. The integrated bookings and access solution transforms meeting rooms and shared spaces from operational headaches into revenue-generating assets.\nWith customers in the UK, Europe, North America and APAC, essensys is deploying a newly launched and simplified go-to-market strategy, positioning the business long-term growth in the flexible workspace and commercial real estate market.\nImportant notices\nThis announcement is not intended to, and does not, constitute or form part of any offer, invitation or the solicitation of an offer to purchase, otherwise acquire, subscribe for, sell or otherwise dispose of, any securities, or the solicitation of any vote or approval in any jurisdiction, pursuant to this announcement or otherwise.\nThe distribution of this announcement in jurisdictions outside the United Kingdom may be restricted by law and therefore persons into whose possession this announcement comes should inform themselves about, and observe, such restrictions. Any failure to comply with the restrictions may constitute a violation of the securities law of any such jurisdiction.\nCanaccord Genuity Limited (\"\nCanaccord Genuity\n\"), which is authorised and regulated in the United Kingdom by the Financial Conduct Authority, is acting exclusively for essensys and for no-one else in connection with the matters referred to in this announcement and will not be responsible to any person other than essensys for providing the protections afforded to clients of Canaccord Genuity, nor for providing advice in relation to the matters referred to herein. Neither Canaccord Genuity nor any of its affiliates (nor any of its or their respective directors, officers, employees, representatives or agents) owes or accepts any duty, liability or responsibility whatsoever (whether direct or indirect, whether in contract, in tort, under statute or otherwise) to any person who is not a client of Canaccord Genuity in connection with the matters referred to in this announcement, or otherwise.\nPrior to publication the information communicated in this announcement was deemed by the Company to constitute inside information for the purposes of article 7 of the Market Abuse Regulation (EU) No 596/2014 as amended by regulation 11 of the Market Abuse (Amendment) (EU Exit) Regulations No 2019/310. With the publication of this announcement, this information is now considered to be in the public domain.\nThe person responsible for the release of this announcement on behalf of the Company is Greg Price, Chief Financial Officer of the Company.\nDisclosure requirements of the Code\nUnder Rule 8.3(a) of the Code, any person who is interested in 1% or more of any class of relevant securities of an offeree company or of any securities exchange offeror (being any offeror other than an offeror in respect of which it has been announced that its offer is, or is likely to be, solely in cash) must make an Opening Position Disclosure following the commencement of the offer period and, if later, following the announcement in which any securities exchange offeror is first identified. An Opening Position Disclosure must contain details of the person's interests and short positions in, and rights to subscribe for, any relevant securities of each of (i) the offeree company and (ii) any securities exchange offeror(s). An Opening Position Disclosure by a person to whom Rule 8.3(a) applies must be made by no later than 3.30 pm (London time) on the 10th business day following the commencement of the offer period and, if appropriate, by no later than 3.30 pm (London time) on the 10th business day following the announcement in which any securities exchange offeror is first identified. Relevant persons who deal in the relevant securities of the offeree company or of a securities exchange offeror prior to the deadline for making an Opening Position Disclosure must instead make a Dealing Disclosure.\nUnder Rule 8.3(b) of the Code, any person who is, or becomes, interested in 1% or more of any class of relevant securities of the offeree company or of any securities exchange offeror must make a Dealing Disclosure if the person deals in any relevant securities of the offeree company or of any securities exchange offeror. A Dealing Disclosure must contain details of the dealing concerned and of the person's interests and short positions in, and rights to subscribe for, any relevant securities of each of (i) the offeree company and (ii) any securities exchange offeror, save to the extent that these details have previously been disclosed under Rule 8. A Dealing Disclosure by a person to whom Rule 8.3(b) applies must be made by no later than 3.30 pm (London time) on the business day following the date of the relevant dealing.\nIf two or more persons act together pursuant to an agreement or understanding, whether formal or informal, to acquire or control an interest in relevant securities of an offeree company or a securities exchange offeror, they will be deemed to be a single person for the purpose of Rule 8.3.\nOpening Position Disclosures must also be made by the offeree company and by any offeror and Dealing Disclosures must also be made by the offeree company, by any offeror and by any persons acting in concert with any of them (see Rules 8.1, 8.2 and 8.4). Details of the offeree and offeror companies in respect of whose relevant securities Opening Position Disclosures and Dealing Disclosures must be made can be found in the Disclosure Table on the Takeover Panel's website at\nwww.thetakeoverpanel.org.uk\n, including details of the number of relevant securities in issue, when the offer period commenced and when any offeror was first identified. You should contact the Panel's Market Surveillance Unit on +44 (0)20 7638 0129 if you are in any doubt as to whether you are required to make an Opening Position Disclosure or a Dealing Disclosure.\nThe defined terms used in this section \"Disclosure requirements of the Code\" are defined in the Code which can be found on the Takeover Panel's website.\nRule 26.1 disclosure\nIn accordance with Rule 26.1 of the Code, a copy of this announcement will be available (subject to certain restrictions relating to persons resident in restricted jurisdictions) at\nhttps://www\n.essensys.tech by no later than 12 noon (London time) on the business day following the date of this announcement. The content of the website referred to in this announcement is not incorporated into and does not form part of this announcement.\nRule 2.9 information\nIn accordance with Rule 2.9 of the Code, essensys confirms that as at the close of business on 23 December 2025 its issued share capital consisted of 64,795,988 ordinary shares of 0.25 pence each which are admitted to trading on the AIM market of London Stock Exchange plc. The International Securities Identification Number for the Company's ordinary shares is GB00BJL1ZF49 and the Legal Entity Identifier is 2138002MSI4WKYNOBS73.\u00a0The Company holds no ordinary shares in treasury.\nAdditional Information\nThis announcement is not intended to, and does not, constitute or form part of any offer, invitation or the solicitation of an offer to purchase, otherwise acquire, subscribe for, sell or otherwise dispose of, any securities, or the solicitation of any vote or approval in any jurisdiction, pursuant to this announcement or otherwise. Any offer, if made, will be made solely by certain offer documentation which will contain the full terms and conditions of any offer, including details of how it may be accepted. The distribution of this announcement in jurisdictions other than the United Kingdom and the availability of any offer to shareholders of essensys who are not resident in the United Kingdom may be affected by the laws of relevant jurisdictions. Therefore any persons who are subject to the laws of any jurisdiction other than the United Kingdom or shareholders of essensys who are not resident in the United Kingdom will need to inform themselves about, and observe any applicable requirements. Any failure to comply with the restrictions may constitute a violation of the securities laws of any such jurisdiction.\nThis announcement has been prepared in accordance with the laws of England and Wales, the Code, the AIM Rules for Companies and the Disclosure Guidance and Transparency Rules and the information disclosed may not be the same as that which would have been prepared in accordance with the laws of jurisdictions outside England and Wales.\nThis information is provided by RNS, the news service of the London Stock Exchange. RNS is approved by the Financial Conduct Authority to act as a Primary Information Provider in the United Kingdom. Terms and conditions relating to the use and distribution of this information may apply. For further information, please contact\nrns@lseg.com\nor visit\nwww.rns.com\n.RNS may use your IP address to confirm compliance with the terms and conditions, to analyse how you engage with the information contained in this communication, and to share such analysis on an anonymised basis with others as part of our commercial services. For further information about how RNS and the London Stock Exchange use the personal data you provide us, please see our\nPrivacy Policy\n.\nEND\nMSCPPUUPGUPQGPW",
          "rns_number": "RNS Number : 2015Q"
        },
        {
          "title": "Holding(s) in Company",
          "date": "21st Jan 2026",
          "announcement_date": "21st Jan 2026",
          "release_time": "2:35 pm",
          "source": "RNS",
          "content": "Today 14:35\nRNS Number : 8290P\nessensys PLC\n21 January 2026\nTR-1: Standard form for notification of major holdings\n1. Issuer Details\nISIN\nGB00BJL1ZF49\nIssuer Name\nESSENSYS PLC\nUK or Non-UK Issuer\nUK\n2. Reason for Notification\nAn acquisition or disposal of voting rights\n3. Details of person subject to the notification obligation\nName\nAmati Global Investors Limited\nCity of registered office (if applicable)\nEdinburgh\nCountry of registered office (if applicable)\nUnited Kingdom\n4. Details of the shareholder\nName\nCity of registered office\nCountry of registered office\nWS Amati Investment Funds\nLeeds\nUnited Kingdom\n5. Date on which the threshold was crossed or reached\n20-Jan-2026\n6. Date on which Issuer notified\n21-Jan-2026\n7. Total positions of person(s) subject to the notification obligation\n% of voting rights attached to shares (total of 8.A)\n% of voting rights through financial instruments (total of 8.B 1 + 8.B 2)\nTotal of both in % (8.A + 8.B)\nTotal number of voting rights held in issuer\nResulting situation on the date on which threshold was crossed or reached\n4.630000\n0.000000\n4.630000\n3002000\nPosition of previous notification (if applicable)\n5.450000\n0.000000\n5.450000\n8. Notified details of the resulting situation on the date on which the threshold was crossed or reached\n8A. Voting rights attached to shares\nClass/Type of shares ISIN code(if possible)\nNumber of direct voting rights (DTR5.1)\nNumber of indirect voting rights (DTR5.2.1)\n% of direct voting rights (DTR5.1)\n% of indirect voting rights (DTR5.2.1)\nGB00BJL1ZF49\n3002000\n4.630000\nSub Total 8.A\n3002000\n4.630000%\n8B1. Financial Instruments according to (DTR5.3.1R.(1) (a))\nType of financial instrument\nExpiration date\nExercise/conversion period\nNumber of voting rights that may be acquired if the instrument is exercised/converted\n% of voting rights\nSub Total 8.B1\n8B2. Financial Instruments with similar economic effect according to (DTR5.3.1R.(1) (b))\nType of financial instrument\nExpiration date\nExercise/conversion period\nPhysical or cash settlement\nNumber of voting rights\n% of voting rights\nSub Total 8.B2\n9. Information in relation to the person subject to the notification obligation\n1. Person subject to the notification obligation is not controlled by any natural person or legal entity and does not control any other undertaking(s) holding directly or indirectly an interest in the (underlying) issuer.\nUltimate controlling person\nName of controlled undertaking\n% of voting rights if it equals or is higher than the notifiable threshold\n% of voting rights through financial instruments if it equals or is higher than the notifiable threshold\nTotal of both if it equals or is higher than the notifiable threshold\n10. In case of proxy voting\nName of the proxy holder\nThe number and % of voting rights held\nThe date until which the voting rights will be held\n11. Additional Information\n12. Date of Completion\n21-Jan-2026\n13. Place Of Completion\nEdinburgh, UK\nThis information is provided by RNS, the news service of the London Stock Exchange. RNS is approved by the Financial Conduct Authority to act as a Primary Information Provider in the United Kingdom. Terms and conditions relating to the use and distribution of this information may apply. For further information, please contact\nrns@lseg.com\nor visit\nwww.rns.com\n.RNS may use your IP address to confirm compliance with the terms and conditions, to analyse how you engage with the information contained in this communication, and to share such analysis on an anonymised basis with others as part of our commercial services. For further information about how RNS and the London Stock Exchange use the personal data you provide us, please see our\nPrivacy Policy\n.\nEND\nHOLSELFLFEMSEDF",
          "rns_number": "RNS Number : 8290P"
        },
        {
          "title": "Form 8.3 - ESSENSYS PLC",
          "date": "21st Jan 2026",
          "announcement_date": "21st Jan 2026",
          "release_time": "11:26 am",
          "source": "RNS",
          "content": "Today 11:26\nRNS Number : 8037P\nAmati Global Investors Ltd\n21 January 2026\nFORM 8.3\nPUBLIC OPENING POSITION DISCLOSURE/DEALING DISCLOSURE BY\nA PERSON WITH INTERESTS IN RELEVANT SECURITIES REPRESENTING 1% OR MORE\nRule 8.3 of the Takeover Code (the \"Code\")\n1. KEY INFORMATION\n(a) Full name of discloser:\nAmati Global Investors Ltd\n(b) Owner or controller of interests and short positions disclosed, if different from 1(a):\nThe naming of nominee or vehicle companies is insufficient. For a trust, the trustee(s), settlor and beneficiaries must be named.\n(c) Name of offeror/offeree in relation to whose relevant securities this form relates:\nUse a separate form for each offeror/offeree\nessensys plc\n(d) If an exempt fund manager connected with an offeror/offeree, state this and specify identity of offeror/offeree:\n(e) Date position held/dealing undertaken:\nFor an opening position disclosure, state the latest practicable date prior to the disclosure\n20 January 2026\n(f) In addition to the company in 1(c) above, is the discloser making disclosures in respect of any other party to the offer?\nIf it is a cash offer or possible cash offer, state \"N/A\"\nYES\n/ NO /\nN/A\nIf YES, specify which:\n2. POSITIONS OF THE PERSON MAKING THE DISCLOSURE\nIf there are positions or rights to subscribe to disclose in more than one class of relevant securities of the offeror or offeree named in 1(c), copy table 2(a) or (b) (as appropriate) for each additional class of relevant security.\n(a) Interests and short positions in the relevant securities of the offeror or offeree to which the disclosure relates following the dealing (if any)\nClass of relevant security:\nOrdinary Shares of 10p\nInterests\nShort positions\nNumber\n%\nNumber\n%\n(1) Relevant securities owned and/or controlled:\n3,002,000\n4.63\n(2) Cash-settled derivatives:\n(3) Stock-settled derivatives (including options) and agreements to purchase/sell:\nTOTAL:\n3,002,000\n4.63\nAll interests and all short positions should be disclosed.\nDetails of any open stock-settled derivative positions (including traded options), or agreements to purchase or sell relevant securities, should be given on a Supplemental Form\u00a08 (Open Positions).\n(b) Rights to subscribe for new securities (including directors' and other employee options)\nClass of relevant security in relation to which subscription right exists:\nDetails, including nature of the rights concerned and relevant percentages:\n3. DEALINGS (IF ANY) BY THE PERSON MAKING THE DISCLOSURE\nWhere there have been dealings in more than one class of relevant securities of the offeror or offeree named in 1(c), copy table 3(a), (b), (c) or (d) (as appropriate) for each additional class of relevant security dealt in.\nThe currency of all prices and other monetary amounts should be stated.\n(a) Purchases and sales\nClass of relevant security\nPurchase/sale\nNumber of securities\nPrice per unit\nOrdinary 0.25p shares\nSale\n500,000\n15p\n(b) Cash-settled derivative transactions\nClass of relevant security\nProduct description\ne.g. CFD\nNature of dealing\ne.g. opening/closing a long/short position, increasing/reducing a long/short position\nNumber of reference securities\nPrice per unit\n(c) Stock-settled derivative transactions (including options)\n(i) Writing, selling, purchasing or varying\nClass of relevant security\nProduct description\ne.g. call option\nWriting, purchasing, selling, varying etc.\nNumber of securities to which option relates\nExercise price per unit\nType\ne.g. American, European etc.\nExpiry date\nOption money paid/ received per unit\n(ii) Exercise\nClass of relevant security\nProduct description\ne.g. call option\nExercising/ exercised against\nNumber of securities\nExercise price per unit\n(d) Other dealings (including subscribing for new securities)\nClass of relevant security\nNature of dealing\ne.g. subscription, conversion\nDetails\nPrice per unit (if applicable)\n4. OTHER INFORMATION\n(a) Indemnity and other dealing arrangements\nDetails of any indemnity or option arrangement, or any agreement or understanding, formal or informal, relating to relevant securities which may be an inducement to deal or refrain from dealing entered into by the person making the disclosure and any party to the offer or any person acting in concert with a party to the offer:\nIrrevocable commitments and letters of intent should not be included. If there are no such agreements, arrangements or understandings, state \"none\"\nNone\n(b) Agreements, arrangements or understandings relating to options or derivatives\nDetails of any agreement, arrangement or understanding, formal or informal, between the person making the disclosure and any other person relating to:\n(i) the voting rights of any relevant securities under any option; or\n(ii) the voting rights or future acquisition or disposal of any relevant securities to which any derivative is referenced:\nIf there are no such agreements, arrangements or understandings, state \"none\"\nNone\n(c) Attachments\nIs a Supplemental Form 8 (Open Positions) attached?\nYES\n/NO\nDate of disclosure:\n21 January 2026\nContact name:\nAndrew Lynn\nTelephone number*:\n0131 503 9105\nPublic disclosures under Rule 8 of the Code must be made to a Regulatory Information Service.\nThe Panel's Market Surveillance Unit is available for consultation in relation to the Code's disclosure requirements on +44 (0)20 7638 0129.\n*If the discloser is a natural person, a telephone number does not need to be included, provided contact information has been provided to the Panel's Market Surveillance Unit.\nThe Code can be viewed on the Panel's website at\nwww.thetakeoverpanel.org.uk\n.\nThis information is provided by RNS, the news service of the London Stock Exchange. RNS is approved by the Financial Conduct Authority to act as a Primary Information Provider in the United Kingdom. Terms and conditions relating to the use and distribution of this information may apply. For further information, please contact\nrns@lseg.com\nor visit\nwww.rns.com\n.RNS may use your IP address to confirm compliance with the terms and conditions, to analyse how you engage with the information contained in this communication, and to share such analysis on an anonymised basis with others as part of our commercial services. For further information about how RNS and the London Stock Exchange use the personal data you provide us, please see our\nPrivacy Policy\n.\nEND\nRETSEIFFFEMSEEF",
          "rns_number": "RNS Number : 8037P"
        }
      ],
      "themes": [
        "operations"
      ]
    },
    "social": {
      "has_data": true,
      "buzz_level": "HIGH",
      "post_count": 400,
      "sentiment_breakdown": {
        "positive": 0.0,
        "neutral": 100.0,
        "negative": 0.0
      }
    },
    "trends": {
      "has_data": true,
      "current_interest": 0,
      "momentum_score": 0,
      "trend_direction": "flat",
      "intelligence_signal": "ACCUMULATION"
    },
    "volatility": {
      "atr_normalized": 9.15,
      "stddev_20d": 0.0
    },
    "risk_flags": {
      "split_risk_level": "NONE",
      "halt_risk": "NONE",
      "penny_stock_risk": "NONE"
    },
    "catalyst_dates": {
      "proxy_date": "2023-04-05"
    }
  },
  "ai_insights": {
    "key_insights": [],
    "hidden_patterns": [],
    "contrarian_signals": [],
    "risk_warnings": [],
    "opportunity_flags": [
      "INFORMATION ASYMMETRY: 61 RNS announcements but only 0 social posts. Market may not have fully digested company developments."
    ],
    "narrative_summary": "ESYS.L shows 0 key patterns worth attention. Primary signal: Stable - flat. AI confidence: MODERATE."
  },
  "crashdash": {
    "industry_intelligence": {
      "category": "SOFTWARE_HARDWARE",
      "name": "Software & Hardware",
      "icon": "\ud83d\udcbb",
      "color": "#6366f1",
      "crash_patterns": [
        "Revenue miss or churn spike",
        "Product delays or tech failures",
        "Customer concentration risks",
        "Competitive disruption (new entrants)",
        "Security breaches or data leaks"
      ],
      "recovery_paths": [
        "New contract wins (large enterprise deals)",
        "Product launches (new features/platforms)",
        "ARR growth acceleration",
        "Strategic partnerships (integrations)",
        "M&A activity (acquirer or target)"
      ],
      "active_patterns": [
        "Revenue miss or churn spike",
        "Product delays or tech failures",
        "Security breaches or data leaks"
      ],
      "relevant_rns_count": 0,
      "key_metrics": [
        "ARR/MRR (recurring revenue)",
        "Customer retention rate",
        "Gross margin (SaaS typically 70%+)",
        "Sales efficiency (CAC payback period)",
        "Product adoption metrics"
      ]
    },
    "panic_analysis": {
      "panic_score": 52.5,
      "signal": "MODERATE_FEAR",
      "interpretation": "\ud83d\udfe1 Cautious sentiment - assess risk/reward",
      "breakdown": {
        "price_destruction": 22.5,
        "volume_death": 14,
        "social_silence": 6,
        "news_sentiment": 10
      },
      "is_opportunity": false,
      "opportunity_reason": "\ud83d\udcca Moderate fear detected - monitor for escalation"
    },
    "fear_vs_facts": {
      "fear_points": [],
      "facts_points": [
        "\ud83d\udcb0 Deep value: 64% off recent peak"
      ],
      "verdict": "\u2705 Facts align with low fear - Normal risk/reward"
    },
    "crashhunter_signals": [
      {
        "type": "BROKEN",
        "icon": "\u274c",
        "text": "Broken",
        "color": "#ef4444"
      },
      {
        "type": "LOW_DATA",
        "icon": "\u2753",
        "text": "Conf 15",
        "color": "#64748b"
      }
    ],
    "catalyst_pipeline": [
      {
        "type": "rns",
        "date": "28th Jan 2026",
        "title": "Directorate change",
        "status": "published",
        "icon": "\ud83d\udce2"
      },
      {
        "type": "rns",
        "date": "26th Jan 2026",
        "title": "Exercise of Options, TVR & Rule 2.9 Announcement",
        "status": "published",
        "icon": "\ud83d\udce2"
      },
      {
        "type": "rns",
        "date": "23rd Jan 2026",
        "title": "Extension of PUSU Deadline",
        "status": "published",
        "icon": "\ud83d\udce2"
      },
      {
        "type": "rns",
        "date": "21st Jan 2026",
        "title": "Holding(s) in Company",
        "status": "published",
        "icon": "\ud83d\udce2"
      },
      {
        "type": "rns",
        "date": "21st Jan 2026",
        "title": "Form 8.3 - ESSENSYS PLC",
        "status": "published",
        "icon": "\ud83d\udce2"
      }
    ],
    "decision_matrix": {
      "decision": "AVOID",
      "reason": "\u274c AVOID - timing BROKEN",
      "checklist": [
        {
          "criterion": "Panic Score",
          "value": "52/100",
          "pass": false,
          "icon": "\ud83d\udfe2"
        },
        {
          "criterion": "Timing Regime",
          "value": "BROKEN",
          "pass": false,
          "icon": "\u274c"
        },
        {
          "criterion": "APEX Quality",
          "value": "40/100",
          "pass": false,
          "icon": "\u26a0\ufe0f"
        },
        {
          "criterion": "Data Confidence",
          "value": "15/100",
          "pass": false,
          "icon": "\u2753"
        },
        {
          "criterion": "Industry Pattern",
          "value": "3 active",
          "pass": true,
          "icon": "\ud83d\udcbb"
        }
      ],
      "pass_rate": "1/5"
    },
    "contrarian_panic": {
      "total_score": 44,
      "band": "\ud83d\udfe2 MILD COMPRESSION (Top 50% - WATCHLIST)",
      "components": {
        "compression": {
          "score": 29,
          "max": 40,
          "signals_30d": 5,
          "signals_60d": 6,
          "signals_90d": 12,
          "signals_per_week": 1.15,
          "total_signals": 12,
          "rsi_extreme_count": 12,
          "rsi_ultra_count": 10,
          "escalation_count": 1,
          "density_score": 12,
          "rsi_score": 10,
          "escalation_score": 4,
          "description": "1.2 signals/week | 12 RSI<20 | 1 escalations | \u26a1 HIGH COMPRESSION"
        },
        "intensification": {
          "score": 10,
          "max": 20,
          "recent_types": [
            "CRASH ZONE BOTTOM",
            "CRASH ZONE BOTTOM",
            "DEEP CRASH BOTTOM"
          ],
          "escalating": true,
          "sustained": false,
          "current_intensity": 2,
          "pattern": "ESCALATING - Getting worse"
        },
        "volume_death": {
          "score": 5,
          "max": 15,
          "relative_volume": 2.61,
          "description": "Elevated volume - Some activity"
        },
        "pop_potential": {
          "score": 0,
          "max": 15,
          "best_historical_rally": 35.6,
          "avg_rally": 14.8,
          "signal_count": 12,
          "description": "Weak history (36%)"
        },
        "accumulation": {
          "score": 0,
          "max": 10,
          "has_accumulation": false,
          "bars_since_accum": 0,
          "description": "No accumulation"
        }
      },
      "ticker": "ESYS.L",
      "signal_date": "2022-10-31",
      "total_signals_history": 12
    }
  },
  "scoring_breakdown": {
    "apex_factors": [
      "Technical quality: +15 (AI_Technical_Score=12.0/20)",
      "Drawdown reversion potential: +17 (Drawdown_Pct=85.0%)",
      "Volume confirmation: +10 (Relative_Volume=2.6)",
      "Pattern reliability: +5 (Rally_Count=1.0)",
      "Upside history: +5 (best_rally_pct=36%)",
      "Round-trip collapse: -12 (lock_in_reached=True, current_return=-64.4%)"
    ],
    "technical_score": {
      "points": 15,
      "ai_score": 12.0,
      "reason": "AI Technical Score 12.0/20 translates to 15/25 points"
    },
    "drawdown_score": {
      "points": 17,
      "drawdown_pct": 85.0,
      "reason": "Drawdown of 85.0% gives 17/20 points"
    },
    "volume_score": {
      "points": 10,
      "rel_volume": 2.61,
      "reason": "Relative volume 2.61x gives 10 points"
    },
    "pattern_score": {
      "points": 5,
      "rally_count": 1.0,
      "reason": "1.0 historical rallies gives 5/15 points"
    },
    "upside_score": {
      "points": 5,
      "best_rally_pct": 35.56,
      "reason": "Best rally of 36% gives 5/20 points"
    },
    "penalties": {
      "total": -12,
      "items": [
        "Round-trip collapse: -12 (lock_in_reached=True, current_return=-64.4%)"
      ]
    }
  },
  "reasons_buy_sell": {
    "reasons_to_buy": [
      {
        "reason": "Proven winner - previously hit lock-in target",
        "tag": "MED",
        "evidence": [
          "lock_in_reached=True"
        ]
      }
    ],
    "reasons_to_sell": [
      {
        "reason": "Deep drawdown - thesis failing",
        "tag": "HIGH",
        "evidence": [
          "current_return_pct=-64.4%",
          "timing_regime=BROKEN"
        ]
      },
      {
        "reason": "Round-trip collapse - pump and dump pattern",
        "tag": "HIGH",
        "evidence": [
          "lock_in_reached=True",
          "current_return_pct=-64.4%"
        ]
      },
      {
        "reason": "Stale signal - not for active trading",
        "tag": "HIGH",
        "evidence": [
          "status=historical",
          "signal_date=2022-10-31"
        ]
      }
    ]
  },
  "trade_plan": {
    "trader_plan": {
      "style": "Avoid",
      "action": "Do not trade - thesis invalidated",
      "sizing": "0%",
      "risk": "N/A",
      "profit_taking": "N/A"
    },
    "investor_plan": {
      "allowed": false,
      "thesis_conditions": "Unlock after AI triangulation + CONFIRMED timing",
      "hold_window": "N/A",
      "risk_management": "N/A"
    }
  },
  "exhaustion": {
    "regime": "BROKEN",
    "run_multiple": -1.81,
    "current_run_pct": -64.44,
    "avg_historical_run_pct": 35.56
  },
  "history_snapshot": {
    "previous_report_date": null,
    "score_change": null,
    "confidence_change": null,
    "new_events_count": 0,
    "new_rns_titles": []
  },
  "commentary": {
    "executive_summary": "Note: this report used historical signals only \u2014 live triangulation (RNS, social, Trends) was not available. Current setup looks like BROKEN with an APEX score of 40/100. Historically there have been 1 rallies (avg. 36%); the position is now -64.4%. Practical take: this is interesting but unconfirmed \u2014 wait for an AI snapshot or clear confirmation before committing size.",
    "bull_case": [
      "No obvious upside without a catalyst"
    ],
    "bear_case": [
      "Very deep drawdown (-64.4%) \u2014 thesis may be broken"
    ],
    "timing_translation": "Thesis looks invalid. Step back or reduce exposure.",
    "confidence_explained": "Confidence 15/100 \u2014 data triangulated from RNS, social and Trends."
  },
  "data_quality": {
    "sources_present": {
      "snapshot_json": false,
      "daily_enrichment_row": true,
      "historical_profile": true,
      "metadata": true,
      "triangulation_events": true,
      "ai_insights": true
    },
    "missing_data": [
      "AI insights from Groq LLM"
    ],
    "confidence_impact": "HIGH",
    "disclaimer": "Data provided as-is. Not financial advice. AIM micro-caps carry significant volatility risk."
  }
}