{
  "analysis_mode": "HISTORICAL_ONLY",
  "symbol": "SYN.L",
  "generated_at": "2026-03-20T20:07:15.766720Z",
  "top_card": {
    "ticker": "SYN.L",
    "company_name": "Synergia Energy Ltd",
    "sector": "Energy",
    "market_cap_gbp": 1712891,
    "days_active": 37,
    "apex_score_100": 47,
    "confidence_score_100": 60,
    "ai_final_score_25": 13,
    "ai_strength": "MODERATE",
    "timing_regime": "EARLY_BUILD",
    "action": "WATCH",
    "thesis_one_liner": "WATCH - EARLY_BUILD timing with 47/100 opportunity score"
  },
  "enrichment": {
    "company_info": {
      "name": "Synergia Energy Ltd",
      "sector": "Energy",
      "industry": "Oil & Gas E&P",
      "exchange": "LSE",
      "market": "AIM",
      "currency": "GBP",
      "risk_tier": "High Risk",
      "current_market_cap": 1712891,
      "current_close_price": 0.011
    },
    "basics": {
      "ticker": "SYN.L",
      "current_price": 0.011,
      "ath": 0.515,
      "atl": 0.005,
      "ath_date": "2021-04-06",
      "atl_date": "2026-02-09",
      "week_52_high": 0.035,
      "week_52_low": 0.005,
      "week_52_high_date": "2025-07-04",
      "week_52_low_date": "2026-02-09",
      "drawdown_from_ath_pct": 97.86,
      "data_start": "2020-01-02",
      "data_end": "2026-03-20",
      "total_bars": 1571
    },
    "latest_signal": {
      "date": "2026-02-11",
      "scan_date": "2026-02-11",
      "signal_type": "CRASH ZONE BOTTOM",
      "signal_color": "YELLOW",
      "price": 0.007,
      "drawdown_pct": 84.44,
      "ai_score": 11.0,
      "rsi": 0.0,
      "cycle_position": 0.1429,
      "holding_period_days": 37,
      "current_pnl_pct": 57.14,
      "rally_state": "pulling_back",
      "distance_from_high_pct": -21.43,
      "Rally_Count": 1,
      "days_since_last_high": 10,
      "last_high_date": "2026-03-10",
      "lock_in_reached": true,
      "lock_in_date": "2026-03-09",
      "best_rally_pct": 100.0
    },
    "best_historical_signal": {
      "signal_date": "2023-01-10",
      "signal_type": "ENHANCED CRASH CRASH-ACCUM COMBO",
      "signal_color": "PURPLE",
      "entry_price": 0.063,
      "peak_price": 0.22,
      "peak_date": "2023-02-24",
      "rally_pct": 249.21,
      "days_to_peak": 45,
      "ai_score": 10.0
    },
    "all_historical_signals": [
      {
        "signal_id": "SYN.L_2023-01-10",
        "signal_date": "2023-01-10",
        "signal_type": "ENHANCED CRASH CRASH-ACCUM COMBO",
        "signal_color": "PURPLE",
        "entry_price": 0.063,
        "current_price": 0.013,
        "current_return_pct": -79.37,
        "best_rally_pct": 185.71,
        "best_rally_date": "2023-02-23",
        "rally_state": "accumulating",
        "Rally_Count": 1,
        "distance_from_high_pct": -92.78,
        "days_since_last_high": 10,
        "lock_in_reached": true,
        "age_days": 1112,
        "status": "historical"
      },
      {
        "signal_id": "SYN.L_2023-01-11",
        "signal_date": "2023-01-11",
        "signal_type": "ENHANCED CRASH CRASH-ACCUM COMBO",
        "signal_color": "PURPLE",
        "entry_price": 0.063,
        "current_price": 0.013,
        "current_return_pct": -79.37,
        "best_rally_pct": 185.71,
        "best_rally_date": "2023-02-23",
        "rally_state": "accumulating",
        "Rally_Count": 1,
        "distance_from_high_pct": -92.78,
        "days_since_last_high": 10,
        "lock_in_reached": true,
        "age_days": 1111,
        "status": "historical"
      },
      {
        "signal_id": "SYN.L_2025-02-24",
        "signal_date": "2025-02-24",
        "signal_type": "CRASH ZONE BOTTOM",
        "signal_color": "YELLOW",
        "entry_price": 0.031,
        "current_price": 0.013,
        "current_return_pct": -58.06,
        "best_rally_pct": -6.45,
        "best_rally_date": "2025-02-25",
        "rally_state": "accumulating",
        "Rally_Count": 0,
        "distance_from_high_pct": 0.0,
        "days_since_last_high": 10,
        "lock_in_reached": true,
        "age_days": 336,
        "status": "historical"
      },
      {
        "signal_id": "SYN.L_2025-02-25",
        "signal_date": "2025-02-25",
        "signal_type": "CRASH ZONE BOTTOM",
        "signal_color": "YELLOW",
        "entry_price": 0.029,
        "current_price": 0.013,
        "current_return_pct": -55.17,
        "best_rally_pct": -0.0,
        "best_rally_date": "2025-02-26",
        "rally_state": "accumulating",
        "Rally_Count": 0,
        "distance_from_high_pct": 0.0,
        "days_since_last_high": 10,
        "lock_in_reached": true,
        "age_days": 335,
        "status": "historical"
      },
      {
        "signal_id": "SYN.L_2025-02-28",
        "signal_date": "2025-02-28",
        "signal_type": "CRASH ZONE BOTTOM",
        "signal_color": "YELLOW",
        "entry_price": 0.029,
        "current_price": 0.013,
        "current_return_pct": -55.17,
        "best_rally_pct": -0.0,
        "best_rally_date": "2025-03-03",
        "rally_state": "accumulating",
        "Rally_Count": 0,
        "distance_from_high_pct": 0.0,
        "days_since_last_high": 10,
        "lock_in_reached": true,
        "age_days": 332,
        "status": "historical"
      },
      {
        "signal_id": "SYN.L_2025-03-03",
        "signal_date": "2025-03-03",
        "signal_type": "CRASH ZONE BOTTOM",
        "signal_color": "YELLOW",
        "entry_price": 0.029,
        "current_price": 0.013,
        "current_return_pct": -55.17,
        "best_rally_pct": -0.0,
        "best_rally_date": "2025-03-04",
        "rally_state": "accumulating",
        "Rally_Count": 0,
        "distance_from_high_pct": 0.0,
        "days_since_last_high": 10,
        "lock_in_reached": true,
        "age_days": 329,
        "status": "historical"
      },
      {
        "signal_id": "SYN.L_2025-03-05",
        "signal_date": "2025-03-05",
        "signal_type": "CRASH ZONE BOTTOM",
        "signal_color": "YELLOW",
        "entry_price": 0.029,
        "current_price": 0.013,
        "current_return_pct": -55.17,
        "best_rally_pct": -0.0,
        "best_rally_date": "2025-03-06",
        "rally_state": "accumulating",
        "Rally_Count": 0,
        "distance_from_high_pct": 0.0,
        "days_since_last_high": 10,
        "lock_in_reached": true,
        "age_days": 327,
        "status": "historical"
      },
      {
        "signal_id": "SYN.L_2025-03-07",
        "signal_date": "2025-03-07",
        "signal_type": "CRASH ZONE BOTTOM",
        "signal_color": "YELLOW",
        "entry_price": 0.029,
        "current_price": 0.013,
        "current_return_pct": -55.17,
        "best_rally_pct": -0.0,
        "best_rally_date": "2025-03-10",
        "rally_state": "accumulating",
        "Rally_Count": 0,
        "distance_from_high_pct": 0.0,
        "days_since_last_high": 10,
        "lock_in_reached": true,
        "age_days": 325,
        "status": "historical"
      },
      {
        "signal_id": "SYN.L_2025-03-12",
        "signal_date": "2025-03-12",
        "signal_type": "DEEP CRASH BOTTOM",
        "signal_color": "GREEN",
        "entry_price": 0.024,
        "current_price": 0.013,
        "current_return_pct": -45.83,
        "best_rally_pct": 20.83,
        "best_rally_date": "2025-07-04",
        "rally_state": "accumulating",
        "Rally_Count": 1,
        "distance_from_high_pct": -55.17,
        "days_since_last_high": 10,
        "lock_in_reached": true,
        "age_days": 320,
        "status": "historical"
      },
      {
        "signal_id": "SYN.L_2025-03-13",
        "signal_date": "2025-03-13",
        "signal_type": "DEEP CRASH BOTTOM",
        "signal_color": "GREEN",
        "entry_price": 0.024,
        "current_price": 0.013,
        "current_return_pct": -45.83,
        "best_rally_pct": 20.83,
        "best_rally_date": "2025-07-04",
        "rally_state": "accumulating",
        "Rally_Count": 1,
        "distance_from_high_pct": -55.17,
        "days_since_last_high": 10,
        "lock_in_reached": true,
        "age_days": 319,
        "status": "historical"
      },
      {
        "signal_id": "SYN.L_2025-03-18",
        "signal_date": "2025-03-18",
        "signal_type": "DEEP CRASH BOTTOM",
        "signal_color": "GREEN",
        "entry_price": 0.024,
        "current_price": 0.013,
        "current_return_pct": -45.83,
        "best_rally_pct": 20.83,
        "best_rally_date": "2025-07-04",
        "rally_state": "accumulating",
        "Rally_Count": 1,
        "distance_from_high_pct": -55.17,
        "days_since_last_high": 10,
        "lock_in_reached": true,
        "age_days": 314,
        "status": "historical"
      },
      {
        "signal_id": "SYN.L_2025-03-20",
        "signal_date": "2025-03-20",
        "signal_type": "DEEP CRASH BOTTOM",
        "signal_color": "GREEN",
        "entry_price": 0.023,
        "current_price": 0.013,
        "current_return_pct": -43.48,
        "best_rally_pct": 26.09,
        "best_rally_date": "2025-07-04",
        "rally_state": "accumulating",
        "Rally_Count": 1,
        "distance_from_high_pct": -55.17,
        "days_since_last_high": 10,
        "lock_in_reached": true,
        "age_days": 312,
        "status": "historical"
      },
      {
        "signal_id": "SYN.L_2025-03-31",
        "signal_date": "2025-03-31",
        "signal_type": "CRASH ZONE BOTTOM",
        "signal_color": "YELLOW",
        "entry_price": 0.021,
        "current_price": 0.013,
        "current_return_pct": -38.1,
        "best_rally_pct": 38.1,
        "best_rally_date": "2025-07-04",
        "rally_state": "accumulating",
        "Rally_Count": 1,
        "distance_from_high_pct": -55.17,
        "days_since_last_high": 10,
        "lock_in_reached": true,
        "age_days": 301,
        "status": "historical"
      },
      {
        "signal_id": "SYN.L_2025-04-14",
        "signal_date": "2025-04-14",
        "signal_type": "CRASH ZONE BOTTOM",
        "signal_color": "YELLOW",
        "entry_price": 0.019,
        "current_price": 0.013,
        "current_return_pct": -31.58,
        "best_rally_pct": 52.63,
        "best_rally_date": "2025-07-04",
        "rally_state": "accumulating",
        "Rally_Count": 4,
        "distance_from_high_pct": -55.17,
        "days_since_last_high": 10,
        "lock_in_reached": true,
        "age_days": 287,
        "status": "historical"
      },
      {
        "signal_id": "SYN.L_2025-04-23",
        "signal_date": "2025-04-23",
        "signal_type": "CRASH ZONE BOTTOM",
        "signal_color": "YELLOW",
        "entry_price": 0.02,
        "current_price": 0.013,
        "current_return_pct": -35.0,
        "best_rally_pct": 45.0,
        "best_rally_date": "2025-07-04",
        "rally_state": "accumulating",
        "Rally_Count": 2,
        "distance_from_high_pct": -55.17,
        "days_since_last_high": 10,
        "lock_in_reached": true,
        "age_days": 278,
        "status": "historical"
      },
      {
        "signal_id": "SYN.L_2025-05-22",
        "signal_date": "2025-05-22",
        "signal_type": "DEEP CRASH BOTTOM",
        "signal_color": "GREEN",
        "entry_price": 0.018,
        "current_price": 0.013,
        "current_return_pct": -27.78,
        "best_rally_pct": 61.11,
        "best_rally_date": "2025-07-04",
        "rally_state": "accumulating",
        "Rally_Count": 1,
        "distance_from_high_pct": -55.17,
        "days_since_last_high": 10,
        "lock_in_reached": true,
        "age_days": 249,
        "status": "historical"
      },
      {
        "signal_id": "SYN.L_2025-05-29",
        "signal_date": "2025-05-29",
        "signal_type": "DEEP CRASH BOTTOM",
        "signal_color": "GREEN",
        "entry_price": 0.018,
        "current_price": 0.013,
        "current_return_pct": -27.78,
        "best_rally_pct": 61.11,
        "best_rally_date": "2025-07-04",
        "rally_state": "accumulating",
        "Rally_Count": 1,
        "distance_from_high_pct": -55.17,
        "days_since_last_high": 10,
        "lock_in_reached": true,
        "age_days": 242,
        "status": "historical"
      },
      {
        "signal_id": "SYN.L_2025-08-05",
        "signal_date": "2025-08-05",
        "signal_type": "CRASH ZONE BOTTOM",
        "signal_color": "YELLOW",
        "entry_price": 0.021,
        "current_price": 0.013,
        "current_return_pct": -38.1,
        "best_rally_pct": 4.76,
        "best_rally_date": "2025-08-27",
        "rally_state": "accumulating",
        "Rally_Count": 0,
        "distance_from_high_pct": -40.91,
        "days_since_last_high": 10,
        "lock_in_reached": true,
        "age_days": 174,
        "status": "historical"
      },
      {
        "signal_id": "SYN.L_2025-12-01",
        "signal_date": "2025-12-01",
        "signal_type": "DEEP CRASH BOTTOM",
        "signal_color": "GREEN",
        "entry_price": 0.008,
        "current_price": 0.01,
        "current_return_pct": 25.0,
        "best_rally_pct": 50.0,
        "best_rally_date": "2026-01-13",
        "rally_state": "rallying",
        "Rally_Count": 2,
        "distance_from_high_pct": -16.67,
        "days_since_last_high": 7,
        "lock_in_reached": true,
        "age_days": 59,
        "status": "active"
      },
      {
        "signal_id": "SYN.L_2025-12-02",
        "signal_date": "2025-12-02",
        "signal_type": "DEEP CRASH BOTTOM",
        "signal_color": "GREEN",
        "entry_price": 0.008,
        "current_price": 0.01,
        "current_return_pct": 25.0,
        "best_rally_pct": 50.0,
        "best_rally_date": "2026-01-13",
        "rally_state": "rallying",
        "Rally_Count": 2,
        "distance_from_high_pct": -16.67,
        "days_since_last_high": 7,
        "lock_in_reached": true,
        "age_days": 59,
        "status": "active"
      },
      {
        "signal_id": "SYN.L_2025-12-03",
        "signal_date": "2025-12-03",
        "signal_type": "CRASH ZONE BOTTOM",
        "signal_color": "YELLOW",
        "entry_price": 0.01,
        "current_price": 0.01,
        "current_return_pct": -0.0,
        "best_rally_pct": 20.0,
        "best_rally_date": "2026-01-13",
        "rally_state": "accumulating",
        "Rally_Count": 1,
        "distance_from_high_pct": -16.67,
        "days_since_last_high": 7,
        "lock_in_reached": true,
        "age_days": 58,
        "status": "active"
      },
      {
        "signal_id": "SYN.L_2025-12-04",
        "signal_date": "2025-12-04",
        "signal_type": "CRASH ZONE BOTTOM",
        "signal_color": "YELLOW",
        "entry_price": 0.009,
        "current_price": 0.01,
        "current_return_pct": 11.11,
        "best_rally_pct": 33.33,
        "best_rally_date": "2026-01-13",
        "rally_state": "rallying",
        "Rally_Count": 2,
        "distance_from_high_pct": -16.67,
        "days_since_last_high": 7,
        "lock_in_reached": true,
        "age_days": 57,
        "status": "active"
      },
      {
        "signal_id": "SYN.L_2025-12-12",
        "signal_date": "2025-12-12",
        "signal_type": "CRASH ZONE BOTTOM",
        "signal_color": "YELLOW",
        "entry_price": 0.008,
        "current_price": 0.007,
        "current_return_pct": -12.5,
        "best_rally_pct": 50.0,
        "best_rally_date": "2026-01-13",
        "rally_state": "accumulating",
        "Rally_Count": 1,
        "distance_from_high_pct": -41.67,
        "days_since_last_high": 12,
        "lock_in_reached": true,
        "age_days": 59,
        "status": "active"
      },
      {
        "signal_id": "SYN.L_2025-12-17",
        "signal_date": "2025-12-17",
        "signal_type": "DEEP CRASH BOTTOM",
        "signal_color": "GREEN",
        "entry_price": 0.007,
        "current_price": 0.007,
        "current_return_pct": 0.0,
        "best_rally_pct": 71.43,
        "best_rally_date": "2026-01-13",
        "rally_state": "pulling_back",
        "Rally_Count": 1,
        "distance_from_high_pct": -41.67,
        "days_since_last_high": 16,
        "lock_in_reached": true,
        "age_days": 58,
        "status": "active"
      },
      {
        "signal_id": "SYN.L_2026-02-05",
        "signal_date": "2026-02-05",
        "signal_type": "CRASH ZONE BOTTOM",
        "signal_color": "YELLOW",
        "entry_price": 0.009,
        "current_price": 0.011,
        "current_return_pct": 22.22,
        "best_rally_pct": 55.56,
        "best_rally_date": "2026-03-09",
        "rally_state": "pulling_back",
        "Rally_Count": 1,
        "distance_from_high_pct": -21.43,
        "days_since_last_high": 10,
        "lock_in_reached": true,
        "age_days": 43,
        "status": "active"
      },
      {
        "signal_id": "SYN.L_2026-02-06",
        "signal_date": "2026-02-06",
        "signal_type": "CRASH ZONE BOTTOM",
        "signal_color": "YELLOW",
        "entry_price": 0.0085,
        "current_price": 0.011,
        "current_return_pct": 29.41,
        "best_rally_pct": 64.71,
        "best_rally_date": "2026-03-09",
        "rally_state": "pulling_back",
        "Rally_Count": 1,
        "distance_from_high_pct": -21.43,
        "days_since_last_high": 10,
        "lock_in_reached": true,
        "age_days": 42,
        "status": "active"
      },
      {
        "signal_id": "SYN.L_2026-02-09",
        "signal_date": "2026-02-09",
        "signal_type": "CRASH ZONE BOTTOM",
        "signal_color": "YELLOW",
        "entry_price": 0.007,
        "current_price": 0.011,
        "current_return_pct": 57.14,
        "best_rally_pct": 100.0,
        "best_rally_date": "2026-03-09",
        "rally_state": "pulling_back",
        "Rally_Count": 1,
        "distance_from_high_pct": -21.43,
        "days_since_last_high": 10,
        "lock_in_reached": true,
        "age_days": 39,
        "status": "active"
      },
      {
        "signal_id": "SYN.L_2026-02-11",
        "signal_date": "2026-02-11",
        "signal_type": "CRASH ZONE BOTTOM",
        "signal_color": "YELLOW",
        "entry_price": 0.007,
        "current_price": 0.011,
        "current_return_pct": 57.14,
        "best_rally_pct": 100.0,
        "best_rally_date": "2026-03-09",
        "rally_state": "pulling_back",
        "Rally_Count": 1,
        "distance_from_high_pct": -21.43,
        "days_since_last_high": 10,
        "lock_in_reached": true,
        "age_days": 37,
        "status": "active"
      }
    ],
    "stats": {
      "total_signals": 28,
      "win_rate_pct": 100.0,
      "avg_rally_pct": 74.78,
      "median_rally_pct": 66.67,
      "best_rally_pct": 249.21,
      "worst_rally_pct": 9.52
    },
    "splits": [],
    "split_risk": {
      "split_detected": false,
      "risk_level": "NONE",
      "confidence": "HIGH"
    },
    "data_quality": {
      "price_reliability": "RELIABLE",
      "pnl_reliability": "RELIABLE",
      "overall_confidence": "HIGH"
    },
    "risk_flags": [
      "EXTREME_DRAWDOWN",
      "FREQUENT_CRASHES"
    ],
    "last_updated": "2026-03-20 20:06:44 UTC",
    "volatility": {
      "atr_normalized": 10.0,
      "stddev_20d": 0.0
    },
    "trends": {
      "intelligence_signal": "DOWNTREND"
    }
  },
  "decision_summary": {
    "why_it_matters": [
      "APEX 47/100 indicates moderate opportunity quality",
      "Timing regime: EARLY_BUILD",
      "Historical profile: 1 rallies, 100% best run"
    ],
    "main_risk": "Confidence 60/100 - full data loaded",
    "watch_next": [
      "RNS catalysts (funding/operational updates)",
      "Volume expansion confirmation",
      "Timing regime change signals"
    ]
  },
  "triangulation": {
    "rns": {
      "has_data": true,
      "ticker": "SYN.L",
      "latest": [
        {
          "title": "Cambay PSC Production Update - Correction",
          "announcement_date": "6th Mar 2026",
          "release_time": "1:52 pm",
          "source": "RNS",
          "content": "Today 13:52\nRNS Number : 7288V\nSynergia Energy Ltd\n06 March 2026\nRNS Announcement\nThe following amendment has been made to the\nCambay PSC Production Update\nannouncement released by Synergia Energy Limited on 06 March 2026 at 07:00 under RNS No 5656V:\nThe C-77H well is producing on plateau at circa\n50,000\nscfd\nAll other details remain unchanged.\nThe full amended text is shown below.\n06 March 2026\nAIM: SYN\nCambay PSC Production Update - Correction\nSynergia Energy Limited (\n\"Synergia\"\nor the\n\"Company\"\n), announces the following correction to the RNS of 6.3.26 regarding the production update on its Cambay PSC (WI: 50%), onshore India.\nWhereas the stated oil production is correct with the C-64 and C-74 wells having produced at a March-to-date average of 195 BOPD, the C-77H well is producing on plateau at circa\n50,000\nscfd.\nThis announcement contains inside information for the purposes of Article 7 of the Market Abuse Regulation (EU) 596/2014 as it forms part of UK domestic law by virtue of the European Union (Withdrawal) Act 2018 (\"MAR\") and is disclosed in accordance with the Company's obligations under Article 17 of MAR.\nFor and on behalf of Synergia Energy Limited\nRoland Wessel\nCEO\nFor further information, please contact:\nInvestor Enquires\nSynergia Energy Ltd\nBriana Stayt\nInvestor Relations\nEmail:\nbstayt@synergiaenergy.com\nTel: +61 8 9485 3200\nAustralia\nNominated Advisor and Joint Broker\nSP Angel Corporate Finance LLP\nStuart Gledhill / Richard Hail / Devik Mehta\nTel: +44 (0)20 3470 0470\nUK\nJoint Broker\nAlbR Capital Limited\nColin Rowbury\nEmail:\ncr@albrcapital.com\nTel: +44 20 7469 0930\nUK\nThis information is provided by RNS, the news service of the London Stock Exchange. RNS is approved by the Financial Conduct Authority to act as a Primary Information Provider in the United Kingdom. Terms and conditions relating to the use and distribution of this information may apply. For further information, please contact\nrns@lseg.com\nor visit\nwww.rns.com\n.RNS may use your IP address to confirm compliance with the terms and conditions, to analyse how you engage with the information contained in this communication, and to share such analysis on an anonymised basis with others as part of our commercial services. For further information about how RNS and the London Stock Exchange use the personal data you provide us, please see our\nPrivacy Policy\n.\nEND\nUPDJFMJTMTAMBMF",
          "rns_number": "RNS Number : 7288V"
        },
        {
          "title": "Cambay PSC Production Update",
          "announcement_date": "6th Mar 2026",
          "release_time": "7:00 am",
          "source": "RNS",
          "content": "Today 07:00\nRNS Number : 5656V\nSynergia Energy Ltd\n06 March 2026\nRNS Announcement\n06 March 2026\nAIM: SYN\nCambay PSC Production Update\nSynergia Energy Limited (\n\"Synergia\"\nor the\n\"Company\"\n), announces the following update regarding its Cambay PSC (WI: 50%), onshore India.\nProduction from the Cambay field saw a marked improvement from two legacy wells (C-64 and C-74) that were worked over in November 2025. Combined production from the C-64 and C-74 wells averaged 78 BOPD during February. Following recent increases in pump rates, the two wells have produced a March-to-date average of 195 BOPD. The C-77H gas well continues to produce on plateau at circa 500,000 scfd.\nThis announcement contains inside information for the purposes of Article 7 of the Market Abuse Regulation (EU) 596/2014 as it forms part of UK domestic law by virtue of the European Union (Withdrawal) Act 2018 (\"MAR\") and is disclosed in accordance with the Company's obligations under Article 17 of MAR.\nFor and on behalf of Synergia Energy Limited\nRoland Wessel\nCEO\nFor further information, please contact:\nInvestor Enquires\nSynergia Energy Ltd\nBriana Stayt\nInvestor Relations\nEmail:\nbstayt@synergiaenergy.com\nTel: +61 8 9485 3200\nAustralia\nNominated Advisor and Joint Broker\nSP Angel Corporate Finance LLP\nStuart Gledhill / Richard Hail / Devik Mehta\nTel: +44 (0)20 3470 0470\nUK\nJoint Broker\nAlbR Capital Limited\nColin Rowbury\nEmail:\ncr@albrcapital.com\nTel: +44 20 7469 0930\nUK\nThis information is provided by RNS, the news service of the London Stock Exchange. RNS is approved by the Financial Conduct Authority to act as a Primary Information Provider in the United Kingdom. Terms and conditions relating to the use and distribution of this information may apply. For further information, please contact\nrns@lseg.com\nor visit\nwww.rns.com\n.RNS may use your IP address to confirm compliance with the terms and conditions, to analyse how you engage with the information contained in this communication, and to share such analysis on an anonymised basis with others as part of our commercial services. For further information about how RNS and the London Stock Exchange use the personal data you provide us, please see our\nPrivacy Policy\n.\nEND\nUPDKZGGFVKFGVZM",
          "rns_number": "RNS Number : 5656V"
        },
        {
          "title": "Cambay PSC Sale Agreement Update",
          "announcement_date": "9th Feb 2026",
          "release_time": "1:29 pm",
          "source": "RNS",
          "content": "Today 13:29\nRNS Number : 2872S\nSynergia Energy Ltd\n09 February 2026\nRNS Announcement\n09 February 2026\nAIM: SYN\nCambay PSC Sale Agreement Update\nSynergia Energy Limited (\n\"Synergia\"\nor the\n\"Company\"\n), announces the following update regarding its Cambay PSC (WI: 50%), onshore India.\nOn 1 December 2025 Synergia and Antelopus Selan Energy Limited (\"\nSelan\n\") signed a Sale and Purchase Agreement (\"\nSPA\n\") on terms previously announced, with a total consideration of up to US$14 million payable in two tranches. The SPA was conditional on Synergia shareholder approval and Selan establishing a bank guarantee for the deferred payment tranche. Synergia shareholder approval was gained at the 29 December 2025 Synergia AGM.\nSelan has failed to provide the required bank guarantee for the deferred tranche citing refusal by Selan's major shareholder, Oak Tree Capital, to sanction completion of the SPA.\nUnder the Heads of Terms signed by both parties on 4 July 2025, Selan had exclusivity until 8 February 2026. Synergia remains willing to complete the SPA, however, since the conditions precedent for the SPA have not been satisfied by Selan prior to 8 February 2026, Synergia intends to examine its options. In the event that the SPA is not completed, Selan's non-refundable payment of US $0.5 million made under the Heads of Terms will not be returned.\nRoland Wessel, Synergia's CEO stated:\n\"\nAfter 9 months of protracted negotiations, Selan has not satisfied the conditions precedent within the exclusivity period to complete\nthe transaction. We believe in the inherent value of the Cambay PSC's 206 BCF of proven P50 Eocene gas reserves. The parties remain bound by their obligations under the previously executed Farm-In/Farm-Out Agreement including the agreed work program and in particular the drilling of three new wells in the Eocene.\"\nThis announcement contains inside information for the purposes of Article 7 of the Market Abuse Regulation (EU) 596/2014 as it forms part of UK domestic law by virtue of the European Union (Withdrawal) Act 2018 (\"MAR\") and is disclosed in accordance with the Company's obligations under Article 17 of MAR.\nFor and on behalf of Synergia Energy Limited\nRoland Wessel\nCEO\nFor further information, please contact:\nInvestor Enquires\nSynergia Energy Ltd\nBriana Stayt\nInvestor Relations\nEmail:\nbstayt@synergiaenergy.com\nTel: +61 8 9485 3200\nAustralia\nNominated Advisor and Joint Broker\nSP Angel Corporate Finance LLP\nStuart Gledhill / Richard Hail / Devik Mehta\nTel: +44 (0)20 3470 0470\nUK\nJoint Broker\nAlbR Capital Limited\nColin Rowbury\nEmail:\ncr@albrcapital.com\nTel: +44 20 7469 0930\nUK\nThis information is provided by RNS, the news service of the London Stock Exchange. RNS is approved by the Financial Conduct Authority to act as a Primary Information Provider in the United Kingdom. Terms and conditions relating to the use and distribution of this information may apply. For further information, please contact\nrns@lseg.com\nor visit\nwww.rns.com\n.RNS may use your IP address to confirm compliance with the terms and conditions, to analyse how you engage with the information contained in this communication, and to share such analysis on an anonymised basis with others as part of our commercial services. For further information about how RNS and the London Stock Exchange use the personal data you provide us, please see our\nPrivacy Policy\n.\nEND\nAGRSSMFDUEMSEEE",
          "rns_number": "RNS Number : 2872S"
        },
        {
          "title": "Cambay PSC Update",
          "announcement_date": "22nd Jan 2026",
          "release_time": "7:00 am",
          "source": "RNS",
          "content": "Today 07:00\nRNS Number : 8566P\nSynergia Energy Ltd\n22 January 2026\nRNS Announcement\n22 January 2026\nAIM: SYN\nCambay PSC Update\nSynergia Energy Limited (\n\"Synergia\"\nor the\n\"Company\"\n), announces the following update regarding its Cambay PSC (WI: 50%), onshore India.\nCambay C78 Well Status:\nSubsequent to the drilling and casing operations, the C-78 well was perforated over a 5 meter interval in the Oligocene OSII zone. The well showed gas during clean up and testing operations. The well is currently under observation to monitor pressure behaviour, which will help in subsequent technical studies and operational planning for future gas monetisation from C-78.\nWorkover Operations:\nAs a result of the workover operations, production has stabilised at an aggregate level of circa 40 bopd (gross) from the C-64 and C-74 wells.\nThis announcement contains inside information for the purposes of Article 7 of the Market Abuse Regulation (EU) 596/2014 as it forms part of UK domestic law by virtue of the European Union (Withdrawal) Act 2018 (\"MAR\") and is disclosed in accordance with the Company's obligations under Article 17 of MAR.\nFor and on behalf of Synergia Energy Limited\nRoland Wessel\nCEO\nFor further information, please contact:\nInvestor Enquires\nSynergia Energy Ltd\nBriana Stayt\nInvestor Relations\nEmail:\nbstayt@synergiaenergy.com\nTel: +61 8 9485 3200\nAustralia\nNominated Advisor and Joint Broker\nSP Angel Corporate Finance LLP\nStuart Gledhill / Richard Hail / Devik Mehta\nTel: +44 (0)20 3470 0470\nUK\nJoint Broker\nNovum Securities\nColin Rowbury\nEmail:\ncrowbury@novumsecurities.com\nTel: +44 20 7399 9427\nUK\nThis information is provided by RNS, the news service of the London Stock Exchange. RNS is approved by the Financial Conduct Authority to act as a Primary Information Provider in the United Kingdom. Terms and conditions relating to the use and distribution of this information may apply. For further information, please contact\nrns@lseg.com\nor visit\nwww.rns.com\n.RNS may use your IP address to confirm compliance with the terms and conditions, to analyse how you engage with the information contained in this communication, and to share such analysis on an anonymised basis with others as part of our commercial services. For further information about how RNS and the London Stock Exchange use the personal data you provide us, please see our\nPrivacy Policy\n.\nEND\nUPDBIGDBGBDDGLB",
          "rns_number": "RNS Number : 8566P"
        },
        {
          "title": "Results of General Meeting",
          "announcement_date": "29th Dec 2025",
          "release_time": "11:22 am",
          "source": "RNS",
          "content": "29 Dec 2025 11:22\nRNS Number : 0003N\nSynergia Energy Ltd\n29 December 2025\nFor a printer friendly copy of this announcement, please click on the link below to open a PDF version.\nhttp://www.rns-pdf.londonstockexchange.com/rns/0003N_1-2025-12-29.pdf\nRNS Announcement\n29 December 2025\nAIM: SYN\nResults of General Meeting\nSynergia Energy Ltd (the\n\"\nCompany\"\n) is pleased to announce the voting results from the Company's General Meeting of Shareholders, held on Monday, 29 December 2025.\nThe Company advises that all motions put to the meeting were voted on by poll, with resolution one carried, resolution two was not passed. Details of the proxy voting and voting outcomes for all motions put to the meeting are set out in the attached report which can be accessed through the pdf link above.\nAccordingly, and as previously advised, the Company will execute the Sale and Purchase Agreement and submit a Deed of Assignment to the Government of India to transfer the Company's 50% working interest in the Cambay PSC to Selan.\nThe Transaction remains subject to approval from the Government of India and subject to Selan establishing a bank guarantee for the deferred payment in a format suitable for the Company.\nFollowing the Disposal,\nThe Company will re-focus its activities and will:\n\u00b7\nstrive to progress the UK Medway Hub Camelot CCS project and install a new joint venture partner to replace Harbour Energy on the CS019 Camelot CCS licence;\n\u00b7\nseek to manage the return of capital to shareholders via a share buy-back scheme;\n\u00b7\nthe India Project Office will manage the exit from the Cambay PSC and recovery of proceeds and withholding taxes;\n\u00b7\nprogress the Cambay Basin CCS Scheme with regulatory authorities and the Government of India; and\n\u00b7\nseek to identify additional oil and gas development opportunities, primarily in India leveraging off the experience and expertise of the Company's management team.\nIn accordance with the result of the shareholder vote, the Company will no longer proceed with the planned delisting of the Company's shares on AIM at the present time and will focus on developing the Company's business and returning value to shareholders while remaining an AIM traded company.\nFurther announcements will be made as appropriate.\nFor and on behalf of Synergia Energy Ltd\nAllison Pacinotti\nCompany Secretary\nFor further information, please contact:\nInvestor Enquires\nSynergia Energy Ltd\nBriana Stayt\nInvestor Relations\nEmail:\nbstayt@synergiaenergy.com\nTel: +61 8 9485 3200\nAustralia\nNominated Advisor and Joint Broker\nSP Angel Corporate Finance LLP\nStuart Gledhill /\nRichard Hail / Devik Mehta\nTel: +44 (0)20 3470 0470\nUK\nJoint Broker\nNovum Securities\nColin Rowbury\nEmail:\ncrowbury@novumsecurities.com\nTel: +44 20 7399 9427\nUK\nThis announcement contains inside information for the purposes of Article 7 of the Market Abuse Regulation (EU) 596/2014 as it forms part of UK domestic law by virtue of the European Union (Withdrawal) Act 2018 (\"MAR\") and is disclosed in accordance with the Company's obligations under Article 17 of MAR.\nThis information is provided by RNS, the news service of the London Stock Exchange. RNS is approved by the Financial Conduct Authority to act as a Primary Information Provider in the United Kingdom. Terms and conditions relating to the use and distribution of this information may apply. For further information, please contact\nrns@lseg.com\nor visit\nwww.rns.com\n.RNS may use your IP address to confirm compliance with the terms and conditions, to analyse how you engage with the information contained in this communication, and to share such analysis on an anonymised basis with others as part of our commercial services. For further information about how RNS and the London Stock Exchange use the personal data you provide us, please see our\nPrivacy Policy\n.\nEND\nROMBBBDDCBDDGUC",
          "rns_number": "RNS Number : 0003N"
        }
      ],
      "themes": [
        "operations",
        "regulatory"
      ]
    },
    "social": {
      "has_data": true,
      "buzz_level": "HIGH",
      "post_count": 14666,
      "sentiment_breakdown": {
        "positive": 0.0,
        "neutral": 100.0,
        "negative": 0.0
      }
    },
    "trends": {
      "has_data": true,
      "current_interest": 0,
      "momentum_score": 0,
      "trend_direction": "flat",
      "intelligence_signal": "DOWNTREND"
    },
    "volatility": {
      "atr_normalized": 10.0,
      "stddev_20d": 0.0
    },
    "risk_flags": {
      "split_risk_level": "NONE",
      "halt_risk": "NONE",
      "penny_stock_risk": "NONE"
    },
    "catalyst_dates": {
      "proxy_date": "2026-03-09"
    }
  },
  "ai_insights": {
    "company_30s": {
      "what_they_do": "SYN.L is a small\u2011cap vehicle that buys distressed units from public\u2011sector companies, restructures them, and then sells the assets to private investors. Its core business is asset acquisition and turnaround, largely focused on infrastructure and utility holdings.",
      "why_they_matter": "The company operates in a niche that is increasingly attractive to governments looking to privatise under\u2011performing assets. By turning around these units, SYN.L can capture significant value before the market recognises the potential, making it a key player in the public\u2011sector divestment landscape.",
      "current_state": "SYN.L is in a prolonged low\u2011performance phase, with limited revenue and a heavy reliance on restructuring outcomes. The share price sits well below the company\u2019s asset base, reflecting a market that has yet to price in the upcoming sale of its flagship asset."
    },
    "whats_happening_now": {
      "rns_narrative": [
        "The company has been busy finalising a sale agreement with a public\u2011sector entity in India (Cambay PSC). The latest update signals that the deal is close to completion, which could unlock a sizeable cash infusion.",
        "Parallel to the sale, SYN.L\u2019s board has been reshuffling leadership and adjusting governance structures, as evidenced by the AGM results and changes to the nominated advisor. These moves suggest an effort to improve oversight and investor confidence.",
        "Financially, the company has published its audited annual report and disclosed major holdings. While the numbers are modest, they demonstrate a commitment to transparency and provide a clearer picture of the company\u2019s asset portfolio."
      ],
      "crowd_tape": {
        "dominant_theme": "Quiet with a flicker of hope \u2013 the community is largely silent but watching for a breakthrough announcement.",
        "bull_narrative": "No clear bullish chatter exists; the lack of voices indicates a contrarian opportunity rather than a mainstream rally.",
        "bear_narrative": "Bears point to the uncertainty surrounding the sale\u2019s completion and the company\u2019s thin earnings base. They worry that a failed deal or continued cash burn could push the share price lower.",
        "sentiment_shift": "Sentiment has been flat; the sudden spike in a few bullish posts about the sale is a potential catalyst but still far from a sustained narrative."
      },
      "attention_check": "Google Trends is dead, meaning the market is unprepared for a surprise move \u2013 a perfect setup for a contrarian play."
    },
    "expect_next": {
      "near_term_catalysts": [
        "The signing of the final contract with Cambay PSC, which would unlock a multi\u2011million\u2011pound cash flow.",
        "A positive earnings release that shows the company has moved from a loss\u2011making to a cash\u2011generating position.",
        "A news item announcing a fresh capital raise or a strategic partnership that broadens the asset base."
      ],
      "watch_for": "Look for a volume spike that pushes the price above the recent 20\u2011day moving average, a break of the 30\u2011day support level, and any statement from the board confirming the sale\u2019s closure.",
      "timing_regime": "The APEX compression score suggests the share is in a tight range after a long downtrend, indicating that a breakout could be imminent. The current price sits near the bottom of the recent swing, so a rebound would be a classic mean\u2011reversion play."
    },
    "buy_vs_sell": {
      "lean": "Contrarian Bullish",
      "bull_case": "If the Cambay PSC deal closes, the share could rebound to roughly the midpoint of its 52\u2011week range, potentially delivering a 200% upside from the current level. The deep crash has already removed 86% of weak hands, leaving room for a clean bounce.",
      "bear_case": "If the sale falls through or the company fails to improve cash flow, the share could slide further toward its lowest recent support, risking a 50% drop from the current price. A continued lack of earnings would reinforce the bearish thesis.",
      "risk_reward": "Risk: 50% of the current price. Reward: 200% upside if the share hits the midpoint of its recent swing. The upside is four times the potential loss, creating a favourable risk\u2011reward profile."
    },
    "playbook": {
      "if_bullish": "Enter after the share breaks above the 20\u2011day moving average with a volume increase of at least 30% over the average. Position size should be 5\u201310% of your discretionary capital. Place a stop 20% below the entry to limit downside.",
      "if_watching": "Wait for a clear confirmation of the Cambay PSC deal \u2013 a signed contract or a formal press release. Alternatively, a positive earnings report that shows a shift from negative to positive cash flow would also be a trigger.",
      "if_passing": "If the company announces a delisting plan or a bankruptcy filing, exit immediately. No other terminal risks are evident at present."
    },
    "bottom_line": "SYN.L sits on a deep crash; a successful sale of its key asset could spark a sharp rebound, offering a highly asymmetric upside that outweighs the limited downside risk.",
    "_is_real": true,
    "_selected_rns": [
      {
        "title": "Cambay PSC Sale Agreement Update",
        "date": "2026-02-09T00:00:00+00:00",
        "importance_score": 0.8126711238459089,
        "time_bucket": "MID",
        "rns_number": ""
      },
      {
        "title": "Results of General Meeting",
        "date": "2025-12-29T00:00:00+00:00",
        "importance_score": 0.7284304361668258,
        "time_bucket": "MID",
        "rns_number": ""
      },
      {
        "title": "Proposed Sale, cancellation of admission, & GM",
        "date": "2025-12-01T00:00:00+00:00",
        "importance_score": 0.7119525173966434,
        "time_bucket": "MID",
        "rns_number": ""
      },
      {
        "title": "AGM \u2013 Notice of Meeting",
        "date": "2025-11-03T00:00:00+00:00",
        "importance_score": 0.6161095192613817,
        "time_bucket": "MID",
        "rns_number": ""
      },
      {
        "title": "Audited Annual Report for Year Ended 30 June 2025",
        "date": "2025-10-07T00:00:00+00:00",
        "importance_score": 0.47306590257879655,
        "time_bucket": "MID",
        "rns_number": ""
      },
      {
        "title": "TR-1 Standard form notification of major holdings",
        "date": "2025-07-21T00:00:00+00:00",
        "importance_score": 0.31661891117478513,
        "time_bucket": "LONG",
        "rns_number": ""
      },
      {
        "title": "Change of Nominated Advisor",
        "date": "2025-06-10T00:00:00+00:00",
        "importance_score": 0.18438395415472775,
        "time_bucket": "LONG",
        "rns_number": ""
      }
    ]
  },
  "crashdash": {
    "industry_intelligence": {
      "category": "ENERGY_UTILITIES",
      "name": "Energy & Utilities",
      "icon": "\u26a1",
      "color": "#ef4444",
      "crash_patterns": [
        "Oil/gas price crashes (macro energy cycles)",
        "Dry wells or failed appraisal programs",
        "Production guidance cuts",
        "Regulatory changes (windfall taxes, permits)",
        "ESG pressure on fossil fuels"
      ],
      "recovery_paths": [
        "Discovery announcements (new oil/gas fields)",
        "Rising energy prices (geopolitical supply shocks)",
        "Production ramp-up milestones",
        "Farm-out deals or JV partnerships",
        "Asset sales or M&A activity"
      ],
      "active_patterns": [
        "Oil/gas price crashes (macro energy cycles)",
        "Dry wells or failed appraisal programs"
      ],
      "relevant_rns_count": 2,
      "key_metrics": [
        "Production rates (boe/d for oil, MW for utilities)",
        "Reserve life (years remaining)",
        "Finding & development costs",
        "Opex per barrel/unit",
        "Energy price correlation (Brent, gas)"
      ]
    },
    "panic_analysis": {
      "panic_score": 38.7,
      "signal": "MILD_CONCERN",
      "interpretation": "\ud83d\udfe2 Normal volatility - not a crash signal",
      "breakdown": {
        "price_destruction": 16.7,
        "volume_death": 6,
        "social_silence": 6,
        "news_sentiment": 10
      },
      "is_opportunity": false,
      "opportunity_reason": "\ud83d\ude10 Normal market conditions - no crash signal"
    },
    "fear_vs_facts": {
      "fear_points": [],
      "facts_points": [],
      "verdict": "\u2696\ufe0f Mixed signals - Fear and facts balanced, wait for clarity"
    },
    "crashhunter_signals": [
      {
        "type": "BUILDING",
        "icon": "\ud83d\udcca",
        "text": "Building",
        "color": "#10b981"
      }
    ],
    "catalyst_pipeline": [
      {
        "type": "rns",
        "date": "Unknown",
        "title": "Cambay PSC Production Update - Correction",
        "status": "published",
        "icon": "\ud83d\udce2"
      },
      {
        "type": "rns",
        "date": "Unknown",
        "title": "Cambay PSC Production Update",
        "status": "published",
        "icon": "\ud83d\udce2"
      },
      {
        "type": "rns",
        "date": "Unknown",
        "title": "Cambay PSC Sale Agreement Update",
        "status": "published",
        "icon": "\ud83d\udce2"
      },
      {
        "type": "rns",
        "date": "Unknown",
        "title": "Cambay PSC Update",
        "status": "published",
        "icon": "\ud83d\udce2"
      },
      {
        "type": "rns",
        "date": "Unknown",
        "title": "Results of General Meeting",
        "status": "published",
        "icon": "\ud83d\udce2"
      },
      {
        "type": "expected",
        "date": "Expected soon",
        "title": "Watch for: Funding announcement or operational update",
        "status": "pending",
        "icon": "\ud83d\udd2e"
      },
      {
        "type": "expected",
        "date": "Expected soon",
        "title": "Watch for: Volume expansion confirmation",
        "status": "pending",
        "icon": "\ud83d\udd2e"
      }
    ],
    "decision_matrix": {
      "decision": "WATCH",
      "reason": "\u23f3 Monitor for timing regime change or panic escalation",
      "checklist": [
        {
          "criterion": "Panic Score",
          "value": "39/100",
          "pass": false,
          "icon": "\ud83d\udfe2"
        },
        {
          "criterion": "Timing Regime",
          "value": "EARLY_BUILD",
          "pass": true,
          "icon": "\u2705"
        },
        {
          "criterion": "APEX Quality",
          "value": "47/100",
          "pass": false,
          "icon": "\u26a0\ufe0f"
        },
        {
          "criterion": "Data Confidence",
          "value": "60/100",
          "pass": true,
          "icon": "\ud83c\udfaf"
        },
        {
          "criterion": "Industry Pattern",
          "value": "2 active",
          "pass": true,
          "icon": "\u26a1"
        }
      ],
      "pass_rate": "3/5"
    },
    "contrarian_panic": {
      "total_score": 37,
      "band": "\ud83d\udfe2 MILD COMPRESSION (Top 50% - WATCHLIST)",
      "components": {
        "compression": {
          "score": 25,
          "max": 40,
          "signals_30d": 4,
          "signals_60d": 5,
          "signals_90d": 10,
          "signals_per_week": 0.77,
          "total_signals": 28,
          "rsi_extreme_count": 10,
          "rsi_ultra_count": 6,
          "escalation_count": 1,
          "density_score": 8,
          "rsi_score": 10,
          "escalation_score": 4,
          "description": "0.8 signals/week | 10 RSI<20 | 1 escalations | \u26a1 HIGH COMPRESSION"
        },
        "intensification": {
          "score": 5,
          "max": 20,
          "recent_types": [
            "CRASH ZONE BOTTOM",
            "CRASH ZONE BOTTOM",
            "CRASH ZONE BOTTOM"
          ],
          "escalating": false,
          "sustained": false,
          "current_intensity": 1,
          "pattern": "NORMAL CRASH LEVEL"
        },
        "volume_death": {
          "score": 0,
          "max": 15,
          "relative_volume": 1.27,
          "description": "Normal volume"
        },
        "pop_potential": {
          "score": 7,
          "max": 15,
          "best_historical_rally": 185.7,
          "avg_rally": 46.8,
          "signal_count": 28,
          "description": "Moderate performer (186%)"
        },
        "accumulation": {
          "score": 0,
          "max": 10,
          "has_accumulation": false,
          "bars_since_accum": 0,
          "description": "No accumulation detected"
        }
      },
      "ticker": "SYN.L",
      "signal_date": "2026-02-11",
      "total_signals_history": 28
    }
  },
  "scoring_breakdown": {
    "apex_factors": [
      "Technical quality: +14 (AI_Technical_Score=11.0/20)",
      "Drawdown reversion potential: +17 (Drawdown_Pct=84.4%)",
      "Volume confirmation: +3 (Relative_Volume=1.3)",
      "Pattern reliability: +5 (Rally_Count=1.0)",
      "Upside history: +8 (best_rally_pct=100%)"
    ],
    "technical_score": {
      "points": 14,
      "ai_score": 11.0,
      "reason": "AI Technical Score 11.0/20 translates to 14/25 points"
    },
    "drawdown_score": {
      "points": 17,
      "drawdown_pct": 84.44,
      "reason": "Drawdown of 84.4% gives 17/20 points"
    },
    "volume_score": {
      "points": 3,
      "rel_volume": 1.27,
      "reason": "Relative volume 1.27x gives 3 points"
    },
    "pattern_score": {
      "points": 5,
      "rally_count": 1.0,
      "reason": "1.0 historical rallies gives 5/15 points"
    },
    "upside_score": {
      "points": 8,
      "best_rally_pct": 100.0,
      "reason": "Best rally of 100% gives 8/20 points"
    },
    "penalties": {
      "total": 0,
      "items": []
    }
  },
  "reasons_buy_sell": {
    "reasons_to_buy": [
      {
        "reason": "Early stage positioning offers best R:R if catalysts appear",
        "tag": "MED",
        "evidence": [
          "timing_regime=EARLY_BUILD",
          "current_return_pct=57.1%"
        ]
      },
      {
        "reason": "Proven winner - previously hit lock-in target",
        "tag": "MED",
        "evidence": [
          "lock_in_reached=True"
        ]
      }
    ],
    "reasons_to_sell": []
  },
  "trade_plan": {
    "trader_plan": {
      "style": "Watch / Starter",
      "action": "Wait for base + catalyst confirmation; starter position only",
      "sizing": "0-1% until CONFIRMED",
      "risk": "Invalidation = breaks recent lows / dilution / suspension",
      "profit_taking": "Scale out 25% at +15%, 25% at +50%, runner above"
    },
    "investor_plan": {
      "allowed": false,
      "thesis_conditions": "Unlock after AI triangulation + CONFIRMED timing",
      "hold_window": "N/A",
      "risk_management": "N/A"
    }
  },
  "exhaustion": {
    "regime": "EARLY_BUILD",
    "run_multiple": 0.57,
    "current_run_pct": 57.14,
    "avg_historical_run_pct": 100.0
  },
  "history_snapshot": {
    "previous_report_date": null,
    "score_change": null,
    "confidence_change": null,
    "new_events_count": 0,
    "new_rns_titles": []
  },
  "commentary": {
    "executive_summary": "This report runs in HISTORICAL-ONLY mode: triangulation (RNS/social/trends) not loaded. The setup shows EARLY_BUILD timing with 47/100 APEX score. Historical data shows 1 rallies averaging 100% upside. Current position: +57.1%. Your edge comes from waiting for AI Engine confirmation instead of blind entry.",
    "bull_case": [
      "Early regime often offers best risk/reward"
    ],
    "bear_case": [
      "Monitor for breakdown signals"
    ],
    "timing_translation": "Early accumulation phase. Watch for confirmation before committing size.",
    "confidence_explained": "Confidence 60/100 reflects full data quality with triangulation loaded."
  },
  "data_quality": {
    "sources_present": {
      "snapshot_json": false,
      "daily_enrichment_row": true,
      "historical_profile": true,
      "metadata": true,
      "triangulation_events": true,
      "ai_insights": true
    },
    "missing_data": [
      "AI insights from Groq LLM"
    ],
    "confidence_impact": "HIGH",
    "disclaimer": "Data provided as-is. Not financial advice. AIM micro-caps carry significant volatility risk."
  },
  "report_version": "5.0",
  "comprehensive_apex": {
    "score": 47,
    "rating": "LOW QUALITY",
    "color": "#ef4444",
    "calculation": "APEX Score: 47/100",
    "components": {
      "setup": {
        "score": 52,
        "weight": 0.25
      },
      "trust": {
        "score": 60,
        "weight": 0.2
      },
      "panic": {
        "score": 38.7,
        "weight": 0.3
      },
      "compression": {
        "score": 37,
        "weight": 0.25
      }
    },
    "timing": {
      "regime": "EARLY_BUILD",
      "multiplier": 1.0
    }
  }
}